Digitales2/Proyecto/old/miscelaneos/Byte_Striping/Rx/bpbs.v
`include "byte_stripingRx.v"
module bpbs ( output reg clk, reset, valid,
    input [7:0] data,
   output reg [7:0] data_in0, data_in1, data_in2, data_in3);

   initial
     begin	
	reset=1;
	clk=0;
	valid=0;
	data_in0 <= 8'h00;
	data_in1 <= 8'h00;
	data_in2 <= 8'h00;
	data_in3 <= 8'h00;
	#5;
	@(posedge clk);
	reset <=0;
	@(posedge clk);
	valid<=1;
	#10;
	@(posedge clk);
	data_in0 <= 8'h01;
	@(posedge clk);
	data_in1<= 8'h02;
	@(posedge clk);
	data_in2 <= 8'h03;
	@(posedge clk);
	data_in3 <= 8'h04;
	@(posedge clk);
	data_in0 <= 8'h05;
	@(posedge clk);
	data_in1<= 8'h06;
	@(posedge clk);
	data_in2 <= 8'h07;
	@(posedge clk);
	data_in3 <= 8'h08;
	@(posedge clk);
	data_in0 <= 8'h09;
	@(posedge clk);
	data_in1<= 8'h10;
	@(posedge clk);
	data_in2 <= 8'h11;
	@(posedge clk);
	data_in3 <= 8'h12;

     end

   always
     begin
	#5 clk = ~clk;	
	
     end

endmodule

Digitales2/Proyecto/old/miscelaneos/Byte_Striping/Rx/byte_stripingRx.v
//Proyecto #1 Circuitos Digitales 2//
module bytestripingRX( input clk, reset, valid,
   output reg[7:0] data,
   input [7:0] data_in0, data_in1, data_in2, data_in3);

   reg [7:0] data_next;

//Indice de registro de los 4 estados,
 parameter [4:0] LaneA = 1,
		 LaneB = 2,
		 LaneC = 3,
		 LaneD = 4,
		 Estado0 =5; //Me da la señal para empezar
		
 reg [7:0] state, next_state; // Se le asignan 8 bits para utlizar one-hot.

//Bloque de Flip Flops
 always @(posedge reset)

	if(reset)begin
	  state <= 8'b00000000; 
	  state[LaneA] <= 1'b1;
	  data<=8'b00000000;
	end
	else if(valid) begin 
		state <= next_state;
		data<=data_next;
	end
		
 always @(posedge clk)

	if(reset)begin
	  state <= 8'b00000000; 
	  state[LaneA] <= 1'b1;
	  data<=8'b00000000;
	end
	else if(valid) begin 
		state <= next_state;
		data<=data_next;
	end

// Bloque de asignacion de los estados y sus transiciones.
 always@(*) begin
	next_state = 8'b00000000;
	data_next=data;  //Evita los Latch inferidos
	case (1'b1)

		state[Estado0]: if(valid) begin next_state [LaneA] = 1'b1;
				
					data_next=data_in0;

			      	end else   next_state [Estado0] = 1'b1;

	
		state[LaneA]: if(valid) begin next_state [LaneB] = 1'b1;
				
					data_next=data_in1;
				
			      end else   next_state [LaneA] = 1'b1;
		
		state[LaneB]: if(valid)begin  next_state [LaneC] = 1'b1;

					data_next=data_in2;			

			      end else   next_state [LaneB] = 1'b1;
		
		state[LaneC]: if(valid) begin next_state [LaneD] = 1'b1;

					data_next=data_in3;

			      end else next_state [LaneC] = 1'b1;
      		
		state[LaneD]: if(valid) begin next_state [LaneA] = 1'b1;

				
					data_next=data_in0;			

			      end else next_state [LaneD] = 1'b1;
	endcase
end
endmodule

Digitales2/Proyecto/old/miscelaneos/Byte_Striping/Rx/tbbs.v
`include "bpbs.v"

module tbbs;

wire clk;
wire [7:0] data, data_in0, data_in1, data_in2, data_in3;

bytestripingRX bytestrip (.clk(clk), .data(data), .reset(reset),.valid(valid),.data_in0(data_in0), .data_in1(data_in1), .data_in2(data_in2), .data_in3(data_in3));
bpbs bancopruebasBS (.clk(clk), .data(data), .reset(reset), .valid(valid),.data_in0(data_in0), .data_in1(data_in1), .data_in2(data_in2), .data_in3(data_in3));

initial begin
    
  //-- Fichero donde almacenar los resultados
  $dumpfile("prueba_Byte_StripingRX.vcd");
  $dumpvars(0, tbbs);
    
  # 600 $display("FIN TestBench");
  $finish;
end


endmodule

Digitales2/Proyecto/old/miscelaneos/Byte_Striping/Rx/prueba_Byte_StripingRX.vcd
$date
	Sat May 26 20:48:24 2018
$end
$version
	Icarus Verilog
$end
$timescale
	1s
$end
$scope module tbbs $end
$var wire 1 ! valid $end
$var wire 1 " reset $end
$var wire 8 # data_in3 [7:0] $end
$var wire 8 $ data_in2 [7:0] $end
$var wire 8 % data_in1 [7:0] $end
$var wire 8 & data_in0 [7:0] $end
$var wire 8 ' data [7:0] $end
$var wire 1 ( clk $end
$scope module bancopruebasBS $end
$var wire 8 ) data [7:0] $end
$var reg 1 ( clk $end
$var reg 8 * data_in0 [7:0] $end
$var reg 8 + data_in1 [7:0] $end
$var reg 8 , data_in2 [7:0] $end
$var reg 8 - data_in3 [7:0] $end
$var reg 1 " reset $end
$var reg 1 ! valid $end
$upscope $end
$scope module bytestrip $end
$var wire 1 ( clk $end
$var wire 8 . data_in0 [7:0] $end
$var wire 8 / data_in1 [7:0] $end
$var wire 8 0 data_in2 [7:0] $end
$var wire 8 1 data_in3 [7:0] $end
$var wire 1 " reset $end
$var wire 1 ! valid $end
$var reg 8 2 data [7:0] $end
$var reg 8 3 data_next [7:0] $end
$var reg 8 4 next_state [7:0] $end
$var reg 8 5 state [7:0] $end
$upscope $end
$upscope $end
$enddefinitions $end
#0
$dumpvars
b10 5
b10 4
b0 3
b0 2
b0 1
b0 0
b0 /
b0 .
b0 -
b0 ,
b0 +
b0 *
b0 )
0(
b0 '
b0 &
b0 %
b0 $
b0 #
1"
0!
$end
#5
b10 4
b10 5
0"
1(
#10
0(
#15
b100 4
1!
1(
#20
0(
#25
b1000 4
b100 5
b1 &
b1 *
b1 .
1(
#30
0(
#35
b10000 4
b10 %
b10 +
b10 /
b1000 5
1(
#40
0(
#45
b1 3
b10 4
b10000 5
b11 $
b11 ,
b11 0
1(
#50
0(
#55
b10 3
b100 4
b100 #
b100 -
b100 1
b1 '
b1 )
b1 2
b10 5
1(
#60
0(
#65
b11 3
b1000 4
b10 '
b10 )
b10 2
b100 5
b101 &
b101 *
b101 .
1(
#70
0(
#75
b100 3
b10000 4
b110 %
b110 +
b110 /
b11 '
b11 )
b11 2
b1000 5
1(
#80
0(
#85
b101 3
b10 4
b100 '
b100 )
b100 2
b10000 5
b111 $
b111 ,
b111 0
1(
#90
0(
#95
b110 3
b100 4
b1000 #
b1000 -
b1000 1
b101 '
b101 )
b101 2
b10 5
1(
#100
0(
#105
b111 3
b1000 4
b110 '
b110 )
b110 2
b100 5
b1001 &
b1001 *
b1001 .
1(
#110
0(
#115
b1000 3
b10000 4
b10000 %
b10000 +
b10000 /
b111 '
b111 )
b111 2
b1000 5
1(
#120
0(
#125
b1001 3
b10 4
b1000 '
b1000 )
b1000 2
b10000 5
b10001 $
b10001 ,
b10001 0
1(
#130
0(
#135
b10000 3
b100 4
b10010 #
b10010 -
b10010 1
b1001 '
b1001 )
b1001 2
b10 5
1(
#140
0(
#145
b10001 3
b1000 4
b10000 '
b10000 )
b10000 2
b100 5
1(
#150
0(
#155
b10010 3
b10000 4
b10001 '
b10001 )
b10001 2
b1000 5
1(
#160
0(
#165
b1001 3
b10 4
b10010 '
b10010 )
b10010 2
b10000 5
1(
#170
0(
#175
b10000 3
b100 4
b1001 '
b1001 )
b1001 2
b10 5
1(
#180
0(
#185
b10001 3
b1000 4
b10000 '
b10000 )
b10000 2
b100 5
1(
#190
0(
#195
b10010 3
b10000 4
b10001 '
b10001 )
b10001 2
b1000 5
1(
#200
0(
#205
b1001 3
b10 4
b10010 '
b10010 )
b10010 2
b10000 5
1(
#210
0(
#215
b10000 3
b100 4
b1001 '
b1001 )
b1001 2
b10 5
1(
#220
0(
#225
b10001 3
b1000 4
b10000 '
b10000 )
b10000 2
b100 5
1(
#230
0(
#235
b10010 3
b10000 4
b10001 '
b10001 )
b10001 2
b1000 5
1(
#240
0(
#245
b1001 3
b10 4
b10010 '
b10010 )
b10010 2
b10000 5
1(
#250
0(
#255
b10000 3
b100 4
b1001 '
b1001 )
b1001 2
b10 5
1(
#260
0(
#265
b10001 3
b1000 4
b10000 '
b10000 )
b10000 2
b100 5
1(
#270
0(
#275
b10010 3
b10000 4
b10001 '
b10001 )
b10001 2
b1000 5
1(
#280
0(
#285
b1001 3
b10 4
b10010 '
b10010 )
b10010 2
b10000 5
1(
#290
0(
#295
b10000 3
b100 4
b1001 '
b1001 )
b1001 2
b10 5
1(
#300
0(
#305
b10001 3
b1000 4
b10000 '
b10000 )
b10000 2
b100 5
1(
#310
0(
#315
b10010 3
b10000 4
b10001 '
b10001 )
b10001 2
b1000 5
1(
#320
0(
#325
b1001 3
b10 4
b10010 '
b10010 )
b10010 2
b10000 5
1(
#330
0(
#335
b10000 3
b100 4
b1001 '
b1001 )
b1001 2
b10 5
1(
#340
0(
#345
b10001 3
b1000 4
b10000 '
b10000 )
b10000 2
b100 5
1(
#350
0(
#355
b10010 3
b10000 4
b10001 '
b10001 )
b10001 2
b1000 5
1(
#360
0(
#365
b1001 3
b10 4
b10010 '
b10010 )
b10010 2
b10000 5
1(
#370
0(
#375
b10000 3
b100 4
b1001 '
b1001 )
b1001 2
b10 5
1(
#380
0(
#385
b10001 3
b1000 4
b10000 '
b10000 )
b10000 2
b100 5
1(
#390
0(
#395
b10010 3
b10000 4
b10001 '
b10001 )
b10001 2
b1000 5
1(
#400
0(
#405
b1001 3
b10 4
b10010 '
b10010 )
b10010 2
b10000 5
1(
#410
0(
#415
b10000 3
b100 4
b1001 '
b1001 )
b1001 2
b10 5
1(
#420
0(
#425
b10001 3
b1000 4
b10000 '
b10000 )
b10000 2
b100 5
1(
#430
0(
#435
b10010 3
b10000 4
b10001 '
b10001 )
b10001 2
b1000 5
1(
#440
0(
#445
b1001 3
b10 4
b10010 '
b10010 )
b10010 2
b10000 5
1(
#450
0(
#455
b10000 3
b100 4
b1001 '
b1001 )
b1001 2
b10 5
1(
#460
0(
#465
b10001 3
b1000 4
b10000 '
b10000 )
b10000 2
b100 5
1(
#470
0(
#475
b10010 3
b10000 4
b10001 '
b10001 )
b10001 2
b1000 5
1(
#480
0(
#485
b1001 3
b10 4
b10010 '
b10010 )
b10010 2
b10000 5
1(
#490
0(
#495
b10000 3
b100 4
b1001 '
b1001 )
b1001 2
b10 5
1(
#500
0(
#505
b10001 3
b1000 4
b10000 '
b10000 )
b10000 2
b100 5
1(
#510
0(
#515
b10010 3
b10000 4
b10001 '
b10001 )
b10001 2
b1000 5
1(
#520
0(
#525
b1001 3
b10 4
b10010 '
b10010 )
b10010 2
b10000 5
1(
#530
0(
#535
b10000 3
b100 4
b1001 '
b1001 )
b1001 2
b10 5
1(
#540
0(
#545
b10001 3
b1000 4
b10000 '
b10000 )
b10000 2
b100 5
1(
#550
0(
#555
b10010 3
b10000 4
b10001 '
b10001 )
b10001 2
b1000 5
1(
#560
0(
#565
b1001 3
b10 4
b10010 '
b10010 )
b10010 2
b10000 5
1(
#570
0(
#575
b10000 3
b100 4
b1001 '
b1001 )
b1001 2
b10 5
1(
#580
0(
#585
b10001 3
b1000 4
b10000 '
b10000 )
b10000 2
b100 5
1(
#590
0(
#595
b10010 3
b10000 4
b10001 '
b10001 )
b10001 2
b1000 5
1(
