Digitales2/Proyecto/old/miscelaneos/define_file.v
`define COM 8'hBC
`define PAD 8'hF7
`define SKP 8'h1C
`define STP 8'hFB
`define SDP 8'h5C
`define END 8'hFD
`define EDB 8'hFE
`define FTS 8'h3C
`define IDL 8'h7C

Digitales2/Proyecto/old/miscelaneos/mux_de_control_forzado/mux_de_control_forzado.v
`include "define_file.v"

module mux_de_control_forzado(
			input [3:0] CONTROL,
            output reg 	VALID,
			input	[7:0] Tx_Buffer,
			input 	CLK,
            output reg [7:0] OUT);
  
	always @ (posedge CLK) begin // Se activa en flanco positivo del CLK

		case (CONTROL) // Selector de entrada
	  		0: OUT <= `COM; //COM
	  		1: OUT <= `PAD; //PAD
	  		2: OUT <= `SKP; //SKP
	  		3: OUT <= `STP; //STP
	  		4: OUT <= `SDP; //SDP
	  		5: OUT <= `END; //END
	  		6: OUT <= `EDB; //EDB
	  		7: OUT <= `FTS; //FTS
	  		8: OUT <= `IDL; //IDL
			9: OUT <= Tx_Buffer; //DATA
			default: OUT <= 0;
		endcase
	end	

	always @ (posedge CLK) begin

		if (CONTROL == 0)

			VALID = 1;

		else

			VALID = VALID;

	end
 
endmodule

Digitales2/Proyecto/old/miscelaneos/mux_de_control_forzado/probador_mux_de_control_forzado.v
module probador_mux_de_control_forzado(CONTROL, CLK, VALID, OUT);

	output reg [3:0] CONTROL;
	output reg CLK;
	output reg VALID;
	output reg [7:0] OUT;

	initial begin 
		CONTROL <= 0;
		CLK = 0;
		OUT <= 8'h00;

		#40 CONTROL <= 1;

		#40 CONTROL <= 2;

		#40 CONTROL <= 3;

		#40 CONTROL <= 4;

		#40 CONTROL <= 5;

		#40 CONTROL <= 6;

		#40 CONTROL <= 7;

		#40 CONTROL <= 8;

		#40 CONTROL <= 9;

		#40 $finish;

	end

	always
		begin #20 CLK <= ~CLK;
	end 

endmodule

Digitales2/Proyecto/old/miscelaneos/mux_de_control_forzado/test_bench.v
`timescale 1ns/100ps

`include "mux_de_control_forzado.v" // Agrega archivo de codigo
`include "probador_mux_de_control_forzado.v" // Agrega archivo de probador

module pruebas_mux_de_control_forzado();

	wire VALID;
	wire CLK;
  	wire [7:0] OUT;
  	input wire [3:0] CONTROL;

  	probador_mux_de_control_forzado probador (CONTROL, CLK, VALID, OUT); 
  	mux_de_control_forzado muxDeControlForzado (CONTROL, VALID, 8'hFF, CLK, OUT); 

  	initial
    		begin
      			$dumpfile("simulation.vcd");
      			$dumpvars;

    	end

endmodule

Digitales2/Proyecto/old/miscelaneos/mux_de_control_forzado/simulation.vcd
$date
	Wed May 23 08:11:44 2018
$end
$version
	Icarus Verilog
$end
$timescale
	100ps
$end
$scope module pruebas_mux_de_control_forzado $end
$var wire 8 ! OUT [7:0] $end
$var wire 1 " VALID $end
$var wire 4 # CONTROL [3:0] $end
$var wire 1 $ CLK $end
$scope module muxDeControlForzado $end
$var wire 8 % Tx_Buffer [7:0] $end
$var wire 4 & CONTROL [3:0] $end
$var wire 1 $ CLK $end
$var reg 8 ' OUT [7:0] $end
$var reg 1 ( VALID $end
$upscope $end
$scope module probador $end
$var reg 1 $ CLK $end
$var reg 4 ) CONTROL [3:0] $end
$var reg 8 * OUT [7:0] $end
$var reg 1 + VALID $end
$upscope $end
$upscope $end
$enddefinitions $end
#0
$dumpvars
x+
b0 *
b0 )
x(
bx '
b0 &
b11111111 %
0$
b0 #
x"
bx !
$end
#200
bx0xxxx00 !
b10111100 '
1(
1$
#400
0$
b1 #
b1 &
b1 )
#600
bx0xxx !
b11110111 '
1$
#800
0$
b10 #
b10 &
b10 )
#1000
b0xxx00 !
b11100 '
1$
#1200
0$
b11 #
b11 &
b11 )
#1400
bx0xx !
b11111011 '
1$
#1600
0$
b100 #
b100 &
b100 )
#1800
b0x0xxx00 !
b1011100 '
1$
#2000
0$
b101 #
b101 &
b101 )
#2200
bx0x !
b11111101 '
1$
#2400
0$
b110 #
b110 &
b110 )
#2600
bx0 !
b11111110 '
1$
#2800
0$
b111 #
b111 &
b111 )
#3000
b0xxxx00 !
b111100 '
1$
#3200
0$
b1000 #
b1000 &
b1000 )
#3400
b0xxxxx00 !
b1111100 '
1$
#3600
0$
b1001 #
b1001 &
b1001 )
#3800
bx !
b11111111 '
1$
