Digitales2/Proyecto/old/miscelaneos/serial_to_parallel/serial_parallel.v

module serial_parallel_cond
    (
    //inputs
    input wire 	    DATA_IN,
    input wire 	    CLK,
    input wire 	    RESET,
    //outputs
    output reg [7:0] DATA_OUT
    );

    reg [2:0] 	    rCurrentState, rNextState;
    reg [6:0] 	    rBuffer;
    reg [7:0]       check;
    reg             Valid;
    reg             Valid_next;
    reg             Valid_neg;
    reg [7:0]       DataOut_next;
    reg             Start;


    always @(*) //HAcer lo mismo con DataOut
        begin
            Valid_next = Valid;
            if (check == 8'hBC)
                begin
                    Valid_next = 1;
                end

        end

    always @(*) //HAcer lo mismo con DataOut
        begin
            DataOut_next = DATA_OUT;
            if (Start == 1)
                begin
                    DataOut_next = 8'hBC;
                end

        end

    always @(*)
        begin
            Valid_neg = ~Valid;
            Start = Valid_neg && Valid_next;
        end    

    always @(posedge CLK)
        begin
            if(RESET)
                begin
                    check <= 0;
                    Valid <= 0;
                    rCurrentState <= 0;
                end
            else
                begin
                    if (Start)
                        begin
                            rCurrentState = 0; 
                        end
                    DATA_OUT <= DataOut_next;
                    Valid <= Valid_next;
                    if (Valid_next == 0)    
                        begin
                            check <= { check[6:0], DATA_IN};
                        end
                    else //Reset = 0 / Valid_next = 1   
                        begin
                            case (rCurrentState) 
                                0:
                                    begin
                                        rBuffer[6] <= DATA_IN;
                                        rCurrentState <= 1;
                                    end
                                1:
                                    begin
                                        rBuffer[5] <= DATA_IN;
                                        rCurrentState <= 2;
                                    end
                                2:
                                    begin
                                        rBuffer[4] <= DATA_IN;
                                        rCurrentState <= 3;
                                    end
                                3:
                                    begin
                                        rBuffer[3] <= DATA_IN;
                                        rCurrentState <= 4;
                                    end
                                4:
                                    begin
                                        rBuffer[2] <= DATA_IN;
                                        rCurrentState <= 5;
                                    end
                                5:
                                    begin
                                        rBuffer[1] <= DATA_IN;
                                        rCurrentState <= 6;
                                    end
                                6:
                                    begin
                                        rBuffer[0] <= DATA_IN;
                                        rCurrentState <= 7;
                                    end
                                7:
                                    begin
                                        DataOut_next <= {rBuffer, DATA_IN};
                                        rCurrentState <= 0;
                                    end
                                default:
                                    begin
                                        rCurrentState <= rCurrentState;
                                    end
                            endcase
                        end
                end 
        end

endmodule

Digitales2/Proyecto/old/miscelaneos/parallel_to_serial/parallel_serial.v

module parallel_serial_cond
  (
   //inputs
   input wire [7:0] DATA_IN,
   input wire 	    CLK,
   input wire 	    RESET, 
   input wire		Valid,
   //outputs
   output reg 	    DATA_OUT
   );

   reg [2:0] 	    rCurrentState, rNextState;
   reg [7:0] 	    rBuffer;

	always @(posedge CLK)
		begin
			if ( RESET)				
				begin
					rCurrentState <= 0;
				end
		end
			
	always @(posedge CLK)
		begin
			if(Valid)
				begin
					case (rCurrentState)
						0:
							begin
								rBuffer <= DATA_IN;
								DATA_OUT <= DATA_IN[7];
								rCurrentState <= 1;
							end
						1: 
							begin
								DATA_OUT <= rBuffer[6];
								rCurrentState <= 2;
							end
						2:
							begin
								DATA_OUT <= rBuffer[5];
								rCurrentState <= 3;
							end
						3:
							begin
								DATA_OUT <= rBuffer[4];
								rCurrentState <= 4;
							end
						4:
							begin
								DATA_OUT <= rBuffer[3];
								rCurrentState <= 5;
							end
						5:
							begin
								DATA_OUT <= rBuffer[2];
								rCurrentState <= 6;
							end
						6:
							begin
								DATA_OUT <= rBuffer[1];
								rCurrentState <= 7;
							end
						7:
							begin
								DATA_OUT <= rBuffer[0];
								rCurrentState <= 0;
							end
						default:
							begin
								rCurrentState <= 0;
							end
					endcase // casex (woResult)
				end
		end

		
endmodule

Digitales2/Proyecto/old/miscelaneos/parallel_to_serial_to_parallel/pcie.v
// Incluir todos los archivos de los modulos

`include "../parallel_to_serial/parallel_serial.v"
`include "../serial_to_parallel/serial_parallel.v"
// Union de modulos de manera estructural

module pcie(
		input RESET,
		input CLK,
		input Valid,
		output [7:0] data
		);

	// Wires de conexion
	wire CLK;
	wire VALID;
	wire [7:0] data0;
	wire [7:0] paralelo0;

	// Paralelo a Serial TX (4 lineas, 4 modulos)
	parallel_serial_cond serial0 (data, CLK, RESET, Valid, dataserial0);
	// Serial a Paralelo RX (4 lineas, 4 modulos)
	serial_parallel_cond parallel0 (dataserial0, CLK, RESET, paralelo0);
	
	
endmodule

Digitales2/Proyecto/old/miscelaneos/parallel_to_serial_to_parallel/probador_pcie.v
module probador_pcie(RESET, CLK, DATA, Valid);

	output reg RESET;
	output reg CLK;
	output reg [7:0] DATA;
	output reg Valid;

	initial begin
		RESET = 1;
		CLK = 0;
		DATA <= 0;
		#3 RESET = 0;
		Valid = 1;

		#16 DATA = 8'b00100101;
		#16 DATA = 8'b10111100; //BC
		#16 DATA = 8'b11111001;
		#16 DATA = 8'b01001111;
		#16 DATA = 8'b10100110;
		#16 DATA = 8'b00111001;
		#16 DATA = 8'b10101000;
		#16 DATA = 8'b11111001;
		#16 DATA = 8'b01001111;

		#100 $finish;

	end

	always 
		begin #1 CLK <= ~CLK;
	end

endmodule

Digitales2/Proyecto/old/miscelaneos/parallel_to_serial_to_parallel/test_bench.v
`timescale 1ns/100ps

`include "pcie.v" // Agrega archivo de codigo
`include "probador_pcie.v" // Agrega archivo de probador

module pruebas_pcie();

	input wire RESET;
  	wire VALID;
	wire CLK;
	wire [7:0] DATA;

  	probador_pcie probador (RESET, CLK, DATA, Valid); 
  	pcie PCIETest (RESET, CLK, Valid, DATA); 

  	initial
    		begin
      			$dumpfile("simulation.vcd");
      			$dumpvars;

    	end

endmodule

Digitales2/Proyecto/old/miscelaneos/parallel_to_serial_to_parallel/simulation.vcd
$date
	Tue May 29 17:33:05 2018
$end
$version
	Icarus Verilog
$end
$timescale
	100ps
$end
$scope module pruebas_pcie $end
$var wire 1 ! Valid $end
$var wire 1 " RESET $end
$var wire 8 # DATA [7:0] $end
$var wire 1 $ CLK $end
$scope module PCIETest $end
$var wire 8 % paralelo0 [7:0] $end
$var wire 1 & dataserial0 $end
$var wire 8 ' data [7:0] $end
$var wire 1 ! Valid $end
$var wire 1 " RESET $end
$var wire 1 $ CLK $end
$scope module parallel0 $end
$var wire 1 " RESET $end
$var wire 1 & DATA_IN $end
$var wire 1 $ CLK $end
$var reg 8 ( DATA_OUT [7:0] $end
$var reg 8 ) DataOut_next [7:0] $end
$var reg 1 * Start $end
$var reg 1 + Valid $end
$var reg 1 , Valid_neg $end
$var reg 1 - Valid_next $end
$var reg 8 . check [7:0] $end
$var reg 7 / rBuffer [6:0] $end
$var reg 3 0 rCurrentState [2:0] $end
$upscope $end
$scope module serial0 $end
$var wire 1 ! Valid $end
$var wire 1 " RESET $end
$var wire 8 1 DATA_IN [7:0] $end
$var wire 1 $ CLK $end
$var reg 1 & DATA_OUT $end
$var reg 8 2 rBuffer [7:0] $end
$var reg 3 3 rCurrentState [2:0] $end
$upscope $end
$upscope $end
$scope module probador $end
$var reg 1 $ CLK $end
$var reg 8 4 DATA [7:0] $end
$var reg 1 " RESET $end
$var reg 1 ! Valid $end
$upscope $end
$upscope $end
$enddefinitions $end
#0
$dumpvars
b0 4
bx 3
bx 2
b0 1
bx 0
bx /
bx .
x-
x,
x+
x*
bx )
bx (
b0 '
x&
bx %
0$
b0 #
1"
x!
$end
#10
0*
1,
0-
b0 3
b0 0
0+
b0 .
1$
#20
0$
#30
b0x .
b1 3
0&
b0 2
1$
1!
0"
#40
0$
#50
b10 3
b0x0 .
1$
#60
0$
#70
b0x00 .
b11 3
1$
#80
0$
#90
b100 3
b0x000 .
1$
#100
0$
#110
b0x0000 .
b101 3
1$
#120
0$
#130
b110 3
b0x00000 .
1$
#140
0$
#150
b0x000000 .
b111 3
1$
#160
0$
#170
b0 3
bx0000000 .
1$
#180
0$
#190
b0 .
b1 3
b100101 2
1$
b100101 #
b100101 '
b100101 1
b100101 4
#200
0$
#210
b10 3
1$
#220
0$
#230
b11 3
1&
1$
#240
0$
#250
b100 3
0&
b1 .
1$
#260
0$
#270
b10 .
b101 3
1$
#280
0$
#290
b110 3
1&
b100 .
1$
#300
0$
#310
b1001 .
b111 3
0&
1$
#320
0$
#330
b0 3
1&
b10010 .
1$
#340
0$
#350
b100101 .
b1 3
b10111100 2
1$
b10111100 #
b10111100 '
b10111100 1
b10111100 4
#360
0$
#370
b10 3
0&
b1001011 .
1$
#380
0$
#390
b10010110 .
b11 3
1&
1$
#400
0$
#410
b100 3
b101101 .
1$
#420
0$
#430
b1011011 .
b101 3
1$
#440
0$
#450
b110 3
b10110111 .
1$
#460
0$
#470
b1101111 .
b111 3
0&
1$
#480
0$
#490
b0 3
b11011110 .
1$
#500
0$
#510
b10111100 )
1*
1-
b10111100 .
b1 3
1&
b11111001 2
1$
b11111001 #
b11111001 '
b11111001 1
b11111001 4
#520
0$
#530
0*
0,
b10 3
b1 0
b1xxxxxx /
1+
b10111100 %
b10111100 (
1$
#540
0$
#550
b10 0
b11xxxxx /
b11 3
1$
#560
0$
#570
b100 3
b11 0
b111xxxx /
1$
#580
0$
#590
b100 0
b1111xxx /
b101 3
1$
#600
0$
#610
b110 3
0&
b101 0
b11111xx /
1$
#620
0$
#630
b110 0
b111110x /
b111 3
1$
#640
0$
#650
b0 3
1&
b111 0
b1111100 /
1$
#660
0$
#670
b0 0
b11111001 )
b1 3
0&
b1001111 2
1$
b1001111 #
b1001111 '
b1001111 1
b1001111 4
#680
0$
#690
b10 3
1&
b1 0
b111100 /
b11111001 %
b11111001 (
1$
#700
0$
#710
b10 0
b11 3
0&
1$
#720
0$
#730
b100 3
b11 0
b101100 /
1$
#740
0$
#750
b100 0
b100100 /
b101 3
1&
1$
#760
0$
#770
b110 3
b101 0
1$
#780
0$
#790
b110 0
b100110 /
b111 3
1$
#800
0$
#810
b0 3
b111 0
b100111 /
1$
#820
0$
#830
b0 0
b1001111 )
b1 3
b10100110 2
1$
b10100110 #
b10100110 '
b10100110 1
b10100110 4
#840
0$
#850
b10 3
0&
b1 0
b1100111 /
b1001111 %
b1001111 (
1$
#860
0$
#870
b10 0
b1000111 /
b11 3
1&
1$
#880
0$
#890
b100 3
0&
b11 0
b1010111 /
1$
#900
0$
#910
b100 0
b101 3
1$
#920
0$
#930
b110 3
1&
b101 0
b1010011 /
1$
#940
0$
#950
b110 0
b111 3
1$
#960
0$
#970
b0 3
0&
b111 0
1$
#980
0$
#990
b0 0
b10100110 )
b1 3
b111001 2
1$
b111001 #
b111001 '
b111001 1
b111001 4
#1000
0$
#1010
b10 3
b1 0
b10011 /
b10100110 %
b10100110 (
1$
#1020
0$
#1030
b10 0
b11 3
1&
1$
#1040
0$
#1050
b100 3
b11 0
1$
#1060
0$
#1070
b100 0
b11011 /
b101 3
1$
#1080
0$
#1090
b110 3
0&
b101 0
b11111 /
1$
#1100
0$
#1110
b110 0
b11101 /
b111 3
1$
#1120
0$
#1130
b0 3
1&
b111 0
b11100 /
1$
#1140
0$
#1150
b0 0
b111001 )
b1 3
b10101000 2
1$
b10101000 #
b10101000 '
b10101000 1
b10101000 4
#1160
0$
#1170
b10 3
0&
b1 0
b1011100 /
b111001 %
b111001 (
1$
#1180
0$
#1190
b10 0
b11 3
1&
1$
#1200
0$
#1210
b100 3
0&
b11 0
1$
#1220
0$
#1230
b100 0
b1010100 /
b101 3
1&
1$
#1240
0$
#1250
b110 3
0&
b101 0
1$
#1260
0$
#1270
b110 0
b111 3
1$
#1280
0$
#1290
b0 3
b111 0
1$
#1300
0$
#1310
b0 0
b10101000 )
b1 3
1&
b11111001 2
1$
b11111001 #
b11111001 '
b11111001 1
b11111001 4
#1320
0$
#1330
b10 3
b1 0
b10101000 %
b10101000 (
1$
#1340
0$
#1350
b10 0
b1110100 /
b11 3
1$
#1360
0$
#1370
b100 3
b11 0
1$
#1380
0$
#1390
b100 0
b1111100 /
b101 3
1$
#1400
0$
#1410
b110 3
0&
b101 0
1$
#1420
0$
#1430
b110 0
b111 3
1$
#1440
0$
#1450
b0 3
1&
b111 0
1$
#1460
0$
#1470
b0 0
b11111001 )
b1 3
0&
b1001111 2
1$
b1001111 #
b1001111 '
b1001111 1
b1001111 4
#1480
0$
#1490
b10 3
1&
b1 0
b111100 /
b11111001 %
b11111001 (
1$
#1500
0$
#1510
b10 0
b11 3
0&
1$
#1520
0$
#1530
b100 3
b11 0
b101100 /
1$
#1540
0$
#1550
b100 0
b100100 /
b101 3
1&
1$
#1560
0$
#1570
b110 3
b101 0
1$
#1580
0$
#1590
b110 0
b100110 /
b111 3
1$
#1600
0$
#1610
b0 3
b111 0
b100111 /
1$
#1620
0$
#1630
b0 0
b1001111 )
b1 3
0&
1$
#1640
0$
#1650
b10 3
1&
b1 0
b1001111 %
b1001111 (
1$
#1660
0$
#1670
b10 0
b11 3
0&
1$
#1680
0$
#1690
b100 3
b11 0
1$
#1700
0$
#1710
b100 0
b101 3
1&
1$
#1720
0$
#1730
b110 3
b101 0
1$
#1740
0$
#1750
b110 0
b111 3
1$
#1760
0$
#1770
b0 3
b111 0
1$
#1780
0$
#1790
b0 0
b1 3
0&
1$
#1800
0$
#1810
b10 3
1&
b1 0
1$
#1820
0$
#1830
b10 0
b11 3
0&
1$
#1840
0$
#1850
b100 3
b11 0
1$
#1860
0$
#1870
b100 0
b101 3
1&
1$
#1880
0$
#1890
b110 3
b101 0
1$
#1900
0$
#1910
b110 0
b111 3
1$
#1920
0$
#1930
b0 3
b111 0
1$
#1940
0$
#1950
b0 0
b1 3
0&
1$
#1960
0$
#1970
b10 3
1&
b1 0
1$
#1980
0$
#1990
b10 0
b11 3
0&
1$
#2000
0$
#2010
b100 3
b11 0
1$
#2020
0$
#2030
b100 0
b101 3
1&
1$
#2040
0$
#2050
b110 3
b101 0
1$
#2060
0$
#2070
b110 0
b111 3
1$
#2080
0$
#2090
b0 3
b111 0
1$
#2100
0$
#2110
b0 0
b1 3
0&
1$
#2120
0$
#2130
b10 3
1&
b1 0
1$
#2140
0$
#2150
b10 0
b11 3
0&
1$
#2160
0$
#2170
b100 3
b11 0
1$
#2180
0$
#2190
b100 0
b101 3
1&
1$
#2200
0$
#2210
b110 3
b101 0
1$
#2220
0$
#2230
b110 0
b111 3
1$
#2240
0$
#2250
b0 3
b111 0
1$
#2260
0$
#2270
b0 0
b1 3
0&
1$
#2280
0$
#2290
b10 3
1&
b1 0
1$
#2300
0$
#2310
b10 0
b11 3
0&
1$
#2320
0$
#2330
b100 3
b11 0
1$
#2340
0$
#2350
b100 0
b101 3
1&
1$
#2360
0$
#2370
b110 3
b101 0
1$
#2380
0$
#2390
b110 0
b111 3
1$
#2400
0$
#2410
b0 3
b111 0
1$
#2420
0$
#2430
b0 0
b1 3
0&
1$
#2440
0$
#2450
b10 3
1&
b1 0
1$
#2460
0$
#2470
b10 0
b11 3
0&
1$
