Digitales2/Proyecto/old/miscelaneos/demux/define_file.v
`define COM 8'hBC
`define PAD 8'hF7
`define SKP 8'h1C
`define STP 8'hFB
`define SDP 8'h5C
`define END 8'hFD
`define EDB 8'hFE
`define FTS 8'h3C
`define IDL 8'h7C

Digitales2/Proyecto/old/miscelaneos/demux/demux.v
`include "define_file.v"

module demux(input [7:0] Rx_buffer,
                	input 	CLK,
                	input 	VALID,
			output reg VALID_OUT,
                        output reg [7:0] DATA);
  
	always @ (posedge CLK) begin

		if (VALID)

			if (Rx_buffer == `STP || Rx_buffer == `SDP || Rx_buffer == `END || Rx_buffer == `IDL || Rx_buffer == `PAD)

				begin
					VALID_OUT <= 0;
					DATA <= DATA;
				end

			else 
	
				begin
					VALID_OUT <= 1;
					DATA <= Rx_buffer;
				end

		else

			DATA = DATA;
 
	end

endmodule

Digitales2/Proyecto/old/miscelaneos/demux/probador_demux.v
`include "define_file.v"

module probador_demux(Rx_buffer, CLK, VALID, VALID_OUT, DATA);

	output reg [7:0] Rx_buffer;
	output reg CLK;
	output reg VALID_OUT;
	output reg VALID;
	output reg [7:0] DATA;

	initial begin 
		Rx_buffer <= 0;
		CLK = 0;
		DATA <= 8'h00;
		VALID = 0;

		#10 VALID = 1;

		#40 Rx_buffer <= `COM;

		#40 Rx_buffer <= `PAD;

		#40 Rx_buffer <= `SKP;

		#40 Rx_buffer <= `STP;

		#40 Rx_buffer <= `SDP;

		#40 Rx_buffer <= `END;

		#40 Rx_buffer <= `EDB;

		#40 Rx_buffer <= `FTS;

		#40 Rx_buffer <= `IDL;

		#40 Rx_buffer <= 8'hFF;

		#40 $finish;

	end

	always
		begin #20 CLK <= ~CLK;
	end 

endmodule

Digitales2/Proyecto/old/miscelaneos/demux/test_bench.v
`timescale 1ns/100ps

`include "demux.v" // Agrega archivo de codigo
`include "probador_demux.v" // Agrega archivo de probador

module pruebas_demux();

	input wire VALID;
	input wire CLK;
	wire VALID_OUT;
  	wire [7:0] DATA;
  	input wire [7:0] Rx_buffer;

  	probador_demux probador (Rx_buffer, CLK, VALID, VALID_OUT, DATA); 
  	demux demux (Rx_buffer, CLK, VALID, VALID_OUT, DATA); 

  	initial
    		begin
      			$dumpfile("simulation.vcd");
      			$dumpvars;

    	end

endmodule

Digitales2/Proyecto/old/miscelaneos/demux/simulation.vcd
$date
	Wed May 16 10:30:36 2018
$end
$version
	Icarus Verilog
$end
$timescale
	100ps
$end
$scope module pruebas_demux $end
$var wire 8 ! DATA [7:0] $end
$var wire 1 " VALID_OUT $end
$var wire 1 # VALID $end
$var wire 8 $ Rx_buffer [7:0] $end
$var wire 1 % CLK $end
$scope module demux $end
$var wire 1 # VALID $end
$var wire 8 & Rx_buffer [7:0] $end
$var wire 1 % CLK $end
$var reg 8 ' DATA [7:0] $end
$var reg 1 ( VALID_OUT $end
$upscope $end
$scope module probador $end
$var reg 1 % CLK $end
$var reg 8 ) DATA [7:0] $end
$var reg 8 * Rx_buffer [7:0] $end
$var reg 1 # VALID $end
$var reg 1 + VALID_OUT $end
$upscope $end
$upscope $end
$enddefinitions $end
#0
$dumpvars
x+
b0 *
b0 )
x(
bx '
b0 &
0%
b0 $
0#
x"
bx !
$end
#100
1#
#200
b0 !
b0 '
1(
1%
#400
0%
#500
b10111100 $
b10111100 &
b10111100 *
#600
bx0xxxx00 !
b10111100 '
1%
#800
0%
#900
b11110111 $
b11110111 &
b11110111 *
#1000
0(
1%
#1200
0%
#1300
b11100 $
b11100 &
b11100 *
#1400
b0xxx00 !
b11100 '
1(
1%
#1600
0%
#1700
b11111011 $
b11111011 &
b11111011 *
#1800
0(
1%
#2000
0%
#2100
b1011100 $
b1011100 &
b1011100 *
#2200
1%
#2400
0%
#2500
b11111101 $
b11111101 &
b11111101 *
#2600
1%
#2800
0%
#2900
b11111110 $
b11111110 &
b11111110 *
#3000
bx0 !
b11111110 '
1(
1%
#3200
0%
#3300
b111100 $
b111100 &
b111100 *
#3400
b0xxxx00 !
b111100 '
1%
#3600
0%
#3700
b1111100 $
b1111100 &
b1111100 *
#3800
0(
1%
#4000
0%
#4100
b11111111 $
b11111111 &
b11111111 *
#4200
bx !
b11111111 '
1(
1%
