Digitales2/temp/probador.v
module probador( // Módulo probador: generador de señales y monitor de datos
	input		sAlr_estr,
	input		sAlr_cond,
	output reg	sLuz,
	output reg	sPrta,
	output reg	sIgn);

	reg 		clk;
	// Bloque de procedimiento, no sintetizable, se recorre una única vez
	// Generalmente, los initial sólo se usan en los testbench o probadores
	// Se recomienda siempre sincronizar con el reloj y utilizar
	// asignaciones no bloqueantes en la generación de señales
	initial begin
		$dumpfile("alarma.vcd");	// Nombre de archivo del "dump"
		$dumpvars;			// Directiva para "dumpear" variables
		// Mensaje que se imprime en consola una vez
		$display ("\t\t\tclk,\tsAlr_estr,\tsAlr_cond,\tsLuz,\tsPrta,\tsIgn");
		// Mensaje que se imprime en consola cada vez que un elemento de la lista cambia
		$monitor($time,"\t%b\t%b\t\t%b\t\t%b\t%b\t%b", clk, sAlr_estr, sAlr_cond, sLuz, sPrta, sIgn);
		{sLuz, sPrta, sIgn} = 3'b0; 	// A los 3 bits, asigna un tipo bit con valor 0.
		repeat (8) begin		// Repite 8 veces
        		@(posedge clk);		// Espera/sincroniza con el flanco positivo del reloj
			{sLuz, sPrta, sIgn} <= {sLuz, sPrta, sIgn} + 1; // Suma 1, asignación no bloqueante
		end
		@(posedge clk);	
		{sLuz, sPrta, sIgn} <= 'b0;	// Asigna un tipo bit con valor 0, de tamaño N
		$finish;			// Termina de almacenar señales
	end
	// Reloj
	initial	clk 	<= 0;			// Valor inicial al reloj, sino siempre será indeterminado
	always	#2 clk 	<= ~clk;		// Hace "toggle" cada 2*10ns
endmodule

Digitales2/temp/alarma_desc_estructural.v
module alarma_desc_estructural (
	output 	sAlr,	// No se indica el tipo de sAlr,  wire implícito
	input 	sLuz,	// No se indica el tipo de sLuz,  wire implícito
	input 	sPrta,	// No se indica el tipo de sPrta, wire implícito
	input 	sIgn);	// No se indica el tipo de sIgn,  wire implícito
	// En las descripciones estructurales, los puertos de entrada y 
	// salida siempre son wires.
	// wire x; // En este escenario, la declaración de x es implícita
	// Compuerta "not" primitiva de Verilog, retardo de propagación = 1
	not #1 gate1(	x,	// Salida, primer puerto
			sIgn);	// Entradas, segundo puerto y otros

	// Compuerta "and" primitiva de Verilog, retardo de propagación = 1
	and #1 gate2(	sAlr,	// Salida, primer puerto
			sLuz,	// Entradas, segundo puerto y otros
			sPrta,
			x);
endmodule

Digitales2/temp/alarma_desc_conductual.v
module alarma_desc_conductual (
	output reg	sAlr,	// sAlr de tipo reg, almacena el valor
	input 		sLuz,	// No se indica el tipo de sLuz,  wire implícito
	input 		sPrta,	// No se indica el tipo de sPrta, wire implícito
	input 		sIgn);	// No se indica el tipo de sIgn,  wire implícito
	// En las descripciones conductuales, los puertos de entrada son wires.
	// Los puertos de salida pueden ser wires o regs, dependiendo de la
	// implementación.

	always @ (*) begin // always combinacional, bloque de procedimiento/comportamiento
	// (*) Lista de sensitividad, entra al "always" ante cualquier cambio
	// en (sLuz or sPrta or sIgn)
		if (sLuz == 1 & sPrta == 1 & sIgn == 0)
			sAlr 	= 1;	// Asignación bloqueante (=)
      		else
			sAlr	= 0;	// Asignación bloqueante (=)
    	end
endmodule

Digitales2/temp/BancoPrueba.v
`timescale 	1ns				/ 100ps
// escala	unidad temporal (valor de "#1") / precisión
// includes de archivos de verilog
// Pueden omitirse y llamarse desde el testbench
`include "alarma_desc_conductual.v"
`include "alarma_desc_estructural.v"
`include "probador.v"

module BancoPruebas; // Testbench
	// Por lo general, las señales en el banco de pruebas son wires.
	// No almacenan un valor, son manejadas por otras instancias de módulos.
	wire sAlr_cond, sAlr_estr, sLuz, sPrta, sIgn;

	// Descripción conductual de alarma
	alarma_desc_conductual	a_cond(	.sAlr		(sAlr_cond),
					.sLuz		(sLuz),
					.sPrta		(sPrta),
					.sIgn		(sIgn)
	);
	// Descripción estructural de alarma
	alarma_desc_estructural	a_estr(	.sAlr		(sAlr_estr),
					.sLuz		(sLuz),
					.sPrta		(sPrta),
					.sIgn		(sIgn)
	);
	// Probador: generador de señales y monitor
	probador probador_(		.sAlr_estr	(sAlr_estr),
					.sAlr_cond	(sAlr_cond),
					.sLuz		(sLuz),
					.sPrta		(sPrta),
					.sIgn		(sIgn)
	);
endmodule

Digitales2/temp/alarma.vcd
$date
	Wed Mar 21 10:29:19 2018
$end
$version
	Icarus Verilog
$end
$timescale
	100ps
$end
$scope module BancoPruebas $end
$var wire 1 ! sAlr_cond $end
$var wire 1 " sAlr_estr $end
$var wire 1 # sIgn $end
$var wire 1 $ sLuz $end
$var wire 1 % sPrta $end
$scope module a_cond $end
$var wire 1 # sIgn $end
$var wire 1 $ sLuz $end
$var wire 1 % sPrta $end
$var reg 1 & sAlr $end
$upscope $end
$scope module a_estr $end
$var wire 1 " sAlr $end
$var wire 1 # sIgn $end
$var wire 1 $ sLuz $end
$var wire 1 % sPrta $end
$var wire 1 ' x $end
$upscope $end
$scope module probador_ $end
$var wire 1 ! sAlr_cond $end
$var wire 1 " sAlr_estr $end
$var reg 1 ( clk $end
$var reg 1 ) sIgn $end
$var reg 1 * sLuz $end
$var reg 1 + sPrta $end
$upscope $end
$upscope $end
$enddefinitions $end
#0
$dumpvars
0+
0*
0)
0(
z'
0&
0%
0$
0#
z"
0!
$end
#10
0"
1'
#20
1)
1#
1(
#30
0'
#40
0(
#60
1+
1%
0)
0#
1(
#70
1'
#80
0(
#100
1)
1#
1(
#110
0'
#120
0(
#140
1*
1$
0+
0%
0)
0#
1(
#150
1'
#160
0(
#180
1)
1#
1(
#190
0'
#200
0(
#220
1&
1!
1+
1%
0)
0#
1(
#230
1'
#240
0(
1"
#260
0&
0!
1)
1#
1(
#270
0'
#280
0(
0"
#300
0*
0$
0+
0%
0)
0#
1(
#310
1'
