Digitales2/Tarea2/registro.v
module Registro ( 
   input wire 	    CLK,
   input wire 	    ENB,
   input wire 	    DIR,
   input wire 	    S_IN,
   input wire [3:0] D,
   input wire [1:0] MODE, 
   output reg 	    S_OUT, 
   output reg [3:0] Q
		  );
   initial
     begin
	S_OUT = 0;
     end
   
   always @(posedge CLK)
     begin
	if (ENB)
	  begin
	     
	     if ( MODE == 2'b10)
               begin
		  S_OUT = 0;	     
		  Q[3:0] <= D[3:0];
	       end
	     if ( MODE == 2'b11)
               S_OUT = 0;
	     
	     if ( MODE == 2'b01)
	       begin
		  S_OUT = 0;       
		  if (DIR)
		    Q[3:0] = {Q[0],Q[3:1]};
		  else
		    Q[3:0] = {Q[2:0],Q[3]};
	       end
	     
	     if ( MODE == 2'b00)
               begin
		  if (DIR)
		    begin
		       //S_OUT = Q[0];
		       Q[3:0] = {S_IN,Q[3:1]};
		    end
		  else
		    begin
		       //S_OUT = Q[3];
		       Q[3:0] = {Q[2:0],S_IN};
		    end
	       end
	     
	  end     
     end // always @ (posedge CLK)
   always @ (negedge CLK)
     begin
	if ( MODE == 2'b00)
          begin
	     if (DIR)
	       begin
		  S_OUT = Q[0];
		  //Q[3:0] = {S_IN,Q[3:1]};
	       end
	     else
	       begin
		  S_OUT = Q[3];
		  //Q[3:0] = {Q[2:0],S_IN};
	       end
	  end
     end
   
endmodule

Digitales2/Tarea2/registro_8b.v
`include "./registro.v"

module Registro_8b ( 
   input wire 	    CLK,
   input wire 	    ENB,
   input wire 	    DIR,
   input wire 	    S_IN,
   input wire [7:0] D,
   input wire [1:0] MODE, 
   output reg 	    S_OUT, 
   output wire [7:0] Q
		  );
   reg 		     r1_in;
   reg		    r0_in;
   wire 	    r1_out;
   wire 	    r0_out; 	    
   reg [1:0] 	    intermode;
 	    
       
   Registro r1(CLK,ENB,DIR,r1_in,D[7:4],intermode,r1_out,Q[7:4]);
   Registro r0(CLK,ENB,DIR,r0_in,D[3:0],intermode,r0_out,Q[3:0]);

   initial
     begin
	S_OUT = 0;
     end
   
   always @(posedge CLK)
     begin	
	if ( MODE == 2'b10)
          begin
	     S_OUT = 0;
	     intermode = 2'b10;	     
	  end
	if ( MODE == 2'b11)
	  begin
	     S_OUT = 0;	     
	     intermode = 2'b11;             
	  end
	if ( MODE == 2'b01)
	  begin
	     S_OUT = 0;       
	     intermode = 2'b00;
	     //r1_in = r0_out;
	     //r0_in = r1_out;
	  end
	
	
	  if ( MODE == 2'b00)
          begin
	     intermode = 2'b00;
	  end
	 
     end 
   always @*

     begin
	if (intermode == 2'b00)
	  begin
	     if (DIR)
	       begin
		  //r1_in = S_IN;
		  //r0_in = r1_out;
		  S_OUT = r0_out;
	       end
	     else
	       begin
		  //r0_in = S_IN;
		  //r1_in = r0_out;
		  S_OUT = r1_out;		  
	       end // else: !if(DIR)
	  end
     end // always @ *
   always @ *
     begin
	if ( MODE == 2'b01)
	  begin
	     //S_OUT = 0;       
	     //intermode = 2'b00;
	     r1_in = r0_out;
	     r0_in = r1_out;
	  end
	else
	  begin
	     if (DIR)
	       begin
		  r1_in = S_IN;
		  r0_in = r1_out;
		  //S_OUT = r0_out;
	       end
	     else
	       begin
		  r0_in = S_IN;
		  r1_in = r0_out;
		  //S_OUT = r1_out;		  
	       end // else: !if(DIR)
	  end     
     end
endmodule

Digitales2/Tarea2/registro_16b.v
`include "./registro_8b.v"

module Registro_16b ( 
   input wire 	    CLK,
   input wire 	    ENB,
   input wire 	    DIR,
   input wire 	    S_IN,
   input wire [15:0] D,
   input wire [1:0] MODE, 
   output reg 	    S_OUT, 
   output wire [15:0] Q
		  );
   reg 		     r1_in;
   reg		    r0_in;
   wire 	    r1_out;
   wire 	    r0_out; 	    
   reg [1:0] 	    intermode;
 	    
       
   Registro_8b r1(CLK,ENB,DIR,r1_in,D[15:8],intermode,r1_out,Q[15:8]);
   Registro_8b r0(CLK,ENB,DIR,r0_in,D[7:0],intermode,r0_out,Q[7:0]);

   initial
     begin
	S_OUT = 0;
     end
   
   always @(posedge CLK)
     begin	
	if ( MODE == 2'b10)
          begin
	     S_OUT = 0;
	     intermode = 2'b10;	     
	  end
	if ( MODE == 2'b11)
	  begin
	     S_OUT = 0;	     
	     intermode = 2'b11;             
	  end
	if ( MODE == 2'b01)
	  begin
	     S_OUT = 0;       
	     intermode = 2'b00;
	     r1_in = r0_out;
	     r0_in = r1_out;
	  end
	
	
	  if ( MODE == 2'b00)
          begin
	     intermode = 2'b00;
	  end
	 
     end 
   always @*

     begin
	if (intermode == 2'b00)
	  begin
	     if (DIR)
	       begin
		  //r1_in = S_IN;
		  //r0_in = r1_out;
		  S_OUT = r0_out;
	       end
	     else
	       begin
		  //r0_in = S_IN;
		  //r1_in = r0_out;
		  S_OUT = r1_out;		  
	       end // else: !if(DIR)
	  end
     end // always @ *
   always @ *
     begin
	if ( MODE == 2'b01)
	  begin
	     //S_OUT = 0;       
	     //intermode = 2'b00;
	     r1_in = r0_out;
	     r0_in = r1_out;
	  end
	else
	  begin
	     if (DIR)
	       begin
		  r1_in = S_IN;
		  r0_in = r1_out;
		  //S_OUT = r0_out;
	       end
	     else
	       begin
		  r0_in = S_IN;
		  r1_in = r0_out;
		  //S_OUT = r1_out;		  
	       end // else: !if(DIR)
	  end     
     end
endmodule

Digitales2/Tarea2/registro_32b.v
`include "./registro_16b.v"

module Registro_32b ( 
   input wire 	    CLK,
   input wire 	    ENB,
   input wire 	    DIR,
   input wire 	    S_IN,
   input wire [31:0] D,
   input wire [1:0] MODE, 
   output reg 	    S_OUT, 
   output wire [31:0] Q
		  );
   reg 		     r1_in;
   reg		    r0_in;
   wire 	    r1_out;
   wire 	    r0_out; 	    
   reg [1:0] 	    intermode;
 	    
       
   Registro_16b r1(CLK,ENB,DIR,r1_in,D[31:16],intermode,r1_out,Q[31:16]);
   Registro_16b r0(CLK,ENB,DIR,r0_in,D[15:0],intermode,r0_out,Q[15:0]);

   initial
     begin
	S_OUT = 0;
     end
   
   always @(posedge CLK)
     begin	
	if ( MODE == 2'b10)
          begin
	     S_OUT = 0;
	     intermode = 2'b10;	     
	  end
	if ( MODE == 2'b11)
	  begin
	     S_OUT = 0;	     
	     intermode = 2'b11;             
	  end
	if ( MODE == 2'b01)
	  begin
	     S_OUT = 0;       
	     intermode = 2'b00;
	     r1_in = r0_out;
	     r0_in = r1_out;
	  end
	
	
	  if ( MODE == 2'b00)
          begin
	     intermode = 2'b00;
	  end
	 
     end 
   always @*

     begin
	if (intermode == 2'b00)
	  begin
	     if (DIR)
	       begin
		  //r1_in = S_IN;
		  //r0_in = r1_out;
		  S_OUT = r0_out;
	       end
	     else
	       begin
		  //r0_in = S_IN;
		  //r1_in = r0_out;
		  S_OUT = r1_out;		  
	       end // else: !if(DIR)
	  end
     end // always @ *
   always @ *
     begin
	if ( MODE == 2'b01)
	  begin
	     //S_OUT = 0;       
	     //intermode = 2'b00;
	     r1_in = r0_out;
	     r0_in = r1_out;
	  end
	else
	  begin
	     if (DIR)
	       begin
		  r1_in = S_IN;
		  r0_in = r1_out;
		  //S_OUT = r0_out;
	       end
	     else
	       begin
		  r0_in = S_IN;
		  r1_in = r0_out;
		  //S_OUT = r1_out;		  
	       end // else: !if(DIR)
	  end     
     end
endmodule

Digitales2/Tarea2/probador_32b.v
module Probador (
		 output reg 	  CLK,
		 output reg 	  ENB,
		 output reg 	  DIR,
		 output reg 	  S_IN,
		 output reg [31:0] D,
		 output reg [1:0] MODE
		 );
		 
   initial
     begin
	#10 CLK = 1'b0;
	ENB = 1;	
	DIR = 0;
	S_IN = 1;
	// Prueba 5, inicialmente el registro se encuentra
	// indeterminado y se carga 0000 en paralelo
	D[31:0] = 32'd4294967293;
	// Demostración de funcionamiento del enable
	#10 MODE[1:0] = 2'b10;
	D[31:0] = 32'd293;	
	#4 D[31:0] = 32'd427293;
	#2 D[31:0] = 32'd42949;
	ENB = 0;
	#4 D[31:0] = 32'd4297293;
	#2 D[31:0] = 32'd967293;
	#40 ENB = 1;
	#100 MODE[1:0] = 2'b01;
	#60 MODE[1:0] = 2'b00;
	S_IN = 0;	
	#40 DIR = ~DIR;
	#40 MODE[1:0] = 2'b10;
	#50 MODE[1:0] = 2'b01;
	#50 DIR = ~DIR;
	
	
     end
   always
     begin
	#1 CLK = ~CLK;
	
     end
   //always 
   //  #25 ENB = ~ENB;
   //always //@ (posedge CLK)
   //  #30 MODE<= (MODE + 2'b01);
   always //@ (posedge CLK)
     #30 D <= (D + 32'd29293);
		 
endmodule

Digitales2/Tarea2/banco_de_pruebas_32b.v
`include "./registro_32b.v"
`include "./probador_32b.v"

module Banco_de_pruebas ();
   
   wire clk;
   wire [31:0] d;
   wire [1:0] mode;
   
  
   Probador t1(clk,enb,dir,s_in,d,mode);
   Registro_32b r1(clk,enb,dir,s_in,d,mode,,);
   
   initial
     begin
	$dumpfile("senales.vcd");
	$dumpvars;
	$display ("Ejecutando simulacion");
	$monitor ($time,,"clk = %b", clk);
	#500 $finish;
     end
endmodule

Digitales2/Tarea2/senales.vcd
$date
	Tue Apr  3 22:55:13 2018
$end
$version
	Icarus Verilog
$end
$timescale
	1s
$end
$scope module Banco_de_pruebas $end
$var wire 1 ! clk $end
$var wire 32 " d [31:0] $end
$var wire 1 # dir $end
$var wire 1 $ enb $end
$var wire 2 % mode [1:0] $end
$var wire 1 & s_in $end
$scope module t1 $end
$var reg 1 ' CLK $end
$var reg 32 ( D [31:0] $end
$var reg 1 ) DIR $end
$var reg 1 * ENB $end
$var reg 2 + MODE [1:0] $end
$var reg 1 , S_IN $end
$upscope $end
$scope module r1 $end
$var wire 1 ! CLK $end
$var wire 32 - D [31:0] $end
$var wire 1 # DIR $end
$var wire 1 $ ENB $end
$var wire 2 . MODE [1:0] $end
$var wire 32 / Q [31:0] $end
$var wire 1 & S_IN $end
$var wire 1 0 r0_out $end
$var wire 1 1 r1_out $end
$var reg 1 2 S_OUT $end
$var reg 2 3 intermode [1:0] $end
$var reg 1 4 r0_in $end
$var reg 1 5 r1_in $end
$scope module r1 $end
$var wire 1 ! CLK $end
$var wire 16 6 D [15:0] $end
$var wire 1 # DIR $end
$var wire 1 $ ENB $end
$var wire 2 7 MODE [1:0] $end
$var wire 16 8 Q [15:0] $end
$var wire 1 9 S_IN $end
$var wire 1 : r0_out $end
$var wire 1 ; r1_out $end
$var reg 1 < S_OUT $end
$var reg 2 = intermode [1:0] $end
$var reg 1 > r0_in $end
$var reg 1 ? r1_in $end
$scope module r1 $end
$var wire 1 ! CLK $end
$var wire 8 @ D [7:0] $end
$var wire 1 # DIR $end
$var wire 1 $ ENB $end
$var wire 2 A MODE [1:0] $end
$var wire 8 B Q [7:0] $end
$var wire 1 C S_IN $end
$var wire 1 D r0_out $end
$var wire 1 E r1_out $end
$var reg 1 F S_OUT $end
$var reg 2 G intermode [1:0] $end
$var reg 1 H r0_in $end
$var reg 1 I r1_in $end
$scope module r1 $end
$var wire 1 ! CLK $end
$var wire 4 J D [3:0] $end
$var wire 1 # DIR $end
$var wire 1 $ ENB $end
$var wire 2 K MODE [1:0] $end
$var wire 1 L S_IN $end
$var reg 4 M Q [3:0] $end
$var reg 1 N S_OUT $end
$upscope $end
$scope module r0 $end
$var wire 1 ! CLK $end
$var wire 4 O D [3:0] $end
$var wire 1 # DIR $end
$var wire 1 $ ENB $end
$var wire 2 P MODE [1:0] $end
$var wire 1 Q S_IN $end
$var reg 4 R Q [3:0] $end
$var reg 1 S S_OUT $end
$upscope $end
$upscope $end
$scope module r0 $end
$var wire 1 ! CLK $end
$var wire 8 T D [7:0] $end
$var wire 1 # DIR $end
$var wire 1 $ ENB $end
$var wire 2 U MODE [1:0] $end
$var wire 8 V Q [7:0] $end
$var wire 1 W S_IN $end
$var wire 1 X r0_out $end
$var wire 1 Y r1_out $end
$var reg 1 Z S_OUT $end
$var reg 2 [ intermode [1:0] $end
$var reg 1 \ r0_in $end
$var reg 1 ] r1_in $end
$scope module r1 $end
$var wire 1 ! CLK $end
$var wire 4 ^ D [3:0] $end
$var wire 1 # DIR $end
$var wire 1 $ ENB $end
$var wire 2 _ MODE [1:0] $end
$var wire 1 ` S_IN $end
$var reg 4 a Q [3:0] $end
$var reg 1 b S_OUT $end
$upscope $end
$scope module r0 $end
$var wire 1 ! CLK $end
$var wire 4 c D [3:0] $end
$var wire 1 # DIR $end
$var wire 1 $ ENB $end
$var wire 2 d MODE [1:0] $end
$var wire 1 e S_IN $end
$var reg 4 f Q [3:0] $end
$var reg 1 g S_OUT $end
$upscope $end
$upscope $end
$upscope $end
$scope module r0 $end
$var wire 1 ! CLK $end
$var wire 16 h D [15:0] $end
$var wire 1 # DIR $end
$var wire 1 $ ENB $end
$var wire 2 i MODE [1:0] $end
$var wire 16 j Q [15:0] $end
$var wire 1 k S_IN $end
$var wire 1 l r0_out $end
$var wire 1 m r1_out $end
$var reg 1 n S_OUT $end
$var reg 2 o intermode [1:0] $end
$var reg 1 p r0_in $end
$var reg 1 q r1_in $end
$scope module r1 $end
$var wire 1 ! CLK $end
$var wire 8 r D [7:0] $end
$var wire 1 # DIR $end
$var wire 1 $ ENB $end
$var wire 2 s MODE [1:0] $end
$var wire 8 t Q [7:0] $end
$var wire 1 u S_IN $end
$var wire 1 v r0_out $end
$var wire 1 w r1_out $end
$var reg 1 x S_OUT $end
$var reg 2 y intermode [1:0] $end
$var reg 1 z r0_in $end
$var reg 1 { r1_in $end
$scope module r1 $end
$var wire 1 ! CLK $end
$var wire 4 | D [3:0] $end
$var wire 1 # DIR $end
$var wire 1 $ ENB $end
$var wire 2 } MODE [1:0] $end
$var wire 1 ~ S_IN $end
$var reg 4 !" Q [3:0] $end
$var reg 1 "" S_OUT $end
$upscope $end
$scope module r0 $end
$var wire 1 ! CLK $end
$var wire 4 #" D [3:0] $end
$var wire 1 # DIR $end
$var wire 1 $ ENB $end
$var wire 2 $" MODE [1:0] $end
$var wire 1 %" S_IN $end
$var reg 4 &" Q [3:0] $end
$var reg 1 '" S_OUT $end
$upscope $end
$upscope $end
$scope module r0 $end
$var wire 1 ! CLK $end
$var wire 8 (" D [7:0] $end
$var wire 1 # DIR $end
$var wire 1 $ ENB $end
$var wire 2 )" MODE [1:0] $end
$var wire 8 *" Q [7:0] $end
$var wire 1 +" S_IN $end
$var wire 1 ," r0_out $end
$var wire 1 -" r1_out $end
$var reg 1 ." S_OUT $end
$var reg 2 /" intermode [1:0] $end
$var reg 1 0" r0_in $end
$var reg 1 1" r1_in $end
$scope module r1 $end
$var wire 1 ! CLK $end
$var wire 4 2" D [3:0] $end
$var wire 1 # DIR $end
$var wire 1 $ ENB $end
$var wire 2 3" MODE [1:0] $end
$var wire 1 4" S_IN $end
$var reg 4 5" Q [3:0] $end
$var reg 1 6" S_OUT $end
$upscope $end
$scope module r0 $end
$var wire 1 ! CLK $end
$var wire 4 7" D [3:0] $end
$var wire 1 # DIR $end
$var wire 1 $ ENB $end
$var wire 2 8" MODE [1:0] $end
$var wire 1 9" S_IN $end
$var reg 4 :" Q [3:0] $end
$var reg 1 ;" S_OUT $end
$upscope $end
$upscope $end
$upscope $end
$upscope $end
$upscope $end
$enddefinitions $end
#0
$dumpvars
0;"
bx :"
x9"
bx 8"
bx 7"
06"
bx 5"
04"
bx 3"
bx 2"
01"
x0"
bx /"
0."
0-"
0,"
x+"
bx *"
bx )"
bx ("
0'"
bx &"
0%"
bx $"
bx #"
0""
bx !"
0~
bx }
bx |
0{
0z
bx y
0x
0w
0v
0u
bx t
bx s
bx r
0q
xp
bx o
0n
0m
0l
xk
bx j
bx i
bx h
0g
bx f
0e
bx d
bx c
0b
bx a
0`
bx _
bx ^
0]
0\
bx [
0Z
0Y
0X
0W
bx V
bx U
bx T
0S
bx R
0Q
bx P
bx O
0N
bx M
0L
bx K
bx J
0I
0H
bx G
0F
0E
0D
0C
bx B
bx A
bx @
0?
0>
bx =
0<
0;
0:
09
bx 8
bx 7
bx 6
05
x4
bx 3
02
01
00
bx /
bx .
bx -
x,
bx +
x*
x)
bx (
x'
x&
bx %
x$
x#
bx "
x!
$end
#10
b1111 J
b1111 O
b1111 ^
b1111 c
b1111 |
b1111 #"
b1111 2"
b1101 7"
b11111111 @
b11111111 T
b11111111 r
b11111101 ("
b1111111111111111 6
b1111111111111101 h
10"
19"
1p
1+"
14
1k
b11111111111111111111111111111101 (
b11111111111111111111111111111101 "
b11111111111111111111111111111101 -
1,
1&
0)
0#
1*
1$
1'
1!
#11
0'
0!
#12
1'
1!
#13
0'
0!
#14
1'
1!
#15
0'
0!
#16
1'
1!
#17
0'
0!
#18
1'
1!
#19
0'
0!
#20
b0 J
b0 O
b0 ^
b0 c
b0 |
b1 #"
b10 2"
b101 7"
b0 @
b0 T
b1 r
b100101 ("
b10 3
b10 7
b10 i
b0 6
b100100101 h
1'
1!
b100100101 (
b100100101 "
b100100101 -
b10 +
b10 %
b10 .
#21
0'
0!
#22
b0 M
b0 R
b0 B
b0 a
b0 f
b0 8
b0 V
b0 !"
b1 &"
b1 t
b10 5"
b101 :"
b100100101 /
b100100101 j
b100101 *"
b10 G
b10 K
b10 P
b10 [
b10 _
b10 d
b10 =
b10 A
b10 U
b10 y
b10 }
b10 $"
b10 /"
b10 3"
b10 8"
b10 o
b10 s
b10 )"
1'
1!
#23
0'
0!
#24
b110 c
b1000 |
b101 #"
b1 2"
b1101 7"
b110 T
b10000101 r
b11101 ("
b110 6
b1000010100011101 h
1'
1!
b1101000010100011101 (
b1101000010100011101 "
b1101000010100011101 -
#25
0'
0!
#26
b0 c
b1010 |
b111 #"
b1100 2"
b101 7"
b0 T
b10100111 r
b11000101 ("
b0 6
b1010011111000101 h
1'
1!
0*
0$
b1010011111000101 (
b1010011111000101 "
b1010011111000101 -
#27
0'
0!
#28
1'
1!
#29
0'
0!
#30
b0 ^
b1 c
b1 |
b1010 #"
b11 2"
b10 7"
b1 T
b11010 r
b110010 ("
b1 6
b1101000110010 h
1'
1!
b10001101000110010 (
b10001101000110010 "
b10001101000110010 -
#31
0'
0!
#32
b1110 c
b1100 |
b10 #"
b111 2"
b1101 7"
b1110 T
b11000010 r
b1111101 ("
b1110 6
b1100001001111101 h
1'
1!
b11101100001001111101 (
b11101100001001111101 "
b11101100001001111101 -
#33
0'
0!
#34
1'
1!
#35
0'
0!
#36
1'
1!
#37
0'
0!
#38
1'
1!
#39
0'
0!
#40
1'
1!
#41
0'
0!
#42
1'
1!
#43
0'
0!
#44
1'
1!
#45
0'
0!
#46
1'
1!
#47
0'
0!
#48
1'
1!
#49
0'
0!
#50
1'
1!
#51
0'
0!
#52
1'
1!
#53
0'
0!
#54
1'
1!
#55
0'
0!
#56
1'
1!
#57
0'
0!
#58
1'
1!
#59
0'
0!
#60
b1111 c
b11 |
b100 #"
b1110 2"
b1010 7"
b1111 T
b110100 r
b11101010 ("
b1111 6
b11010011101010 h
b11110011010011101010 (
b11110011010011101010 "
b11110011010011101010 -
1'
1!
#61
0'
0!
#62
1'
1!
#63
0'
0!
#64
1'
1!
#65
0'
0!
#66
1'
1!
#67
0'
0!
#68
1'
1!
#69
0'
0!
#70
1'
1!
#71
0'
0!
#72
b1010 :"
b1110 5"
b11101010 *"
b100 &"
b11 !"
b11010011101010 j
b110100 t
b1111 f
b11110011010011101010 /
b1111 8
b1111 V
1'
1!
1*
1$
#73
0'
0!
#74
1'
1!
#75
0'
0!
#76
1'
1!
#77
0'
0!
#78
1'
1!
#79
0'
0!
#80
1'
1!
#81
0'
0!
#82
1'
1!
#83
0'
0!
#84
1'
1!
#85
0'
0!
#86
1'
1!
#87
0'
0!
#88
1'
1!
#89
0'
0!
#90
b1010 |
b111 #"
b101 2"
b111 7"
b10100111 r
b1010111 ("
b1010011101010111 h
b11111010011101010111 (
b11111010011101010111 "
b11111010011101010111 -
1'
1!
#91
0'
0!
#92
b111 :"
b101 5"
b1010111 *"
b111 &"
b1010 !"
b11111010011101010111 /
b1010011101010111 j
b10100111 t
1'
1!
#93
0'
0!
#94
1'
1!
#95
0'
0!
#96
1'
1!
#97
0'
0!
#98
1'
1!
#99
0'
0!
#100
1'
1!
#101
0'
0!
#102
1'
1!
#103
0'
0!
#104
1'
1!
#105
0'
0!
#106
1'
1!
#107
0'
0!
#108
1'
1!
#109
0'
0!
#110
1'
1!
#111
0'
0!
#112
1'
1!
#113
0'
0!
#114
1'
1!
#115
0'
0!
#116
1'
1!
#117
0'
0!
#118
1'
1!
#119
0'
0!
#120
b1 ^
b0 c
b1 |
b1001 #"
b1100 2"
b100 7"
b10000 T
b11001 r
b11000100 ("
b10000 6
b1100111000100 h
b100000001100111000100 (
b100000001100111000100 "
b100000001100111000100 -
1'
1!
#121
0'
0!
#122
b1 a
b0 f
b10000 8
b10000 V
b1 !"
b1001 &"
b11001 t
b1100 5"
b100 :"
b100000001100111000100 /
b1100111000100 j
b11000100 *"
1'
1!
#123
0'
0!
#124
1'
1!
#125
0'
0!
#126
1'
1!
#127
0'
0!
#128
1'
1!
#129
0'
0!
#130
1'
1!
#131
0'
0!
#132
1'
1!
#133
0'
0!
#134
1'
1!
#135
0'
0!
#136
1'
1!
#137
0'
0!
#138
1'
1!
#139
0'
0!
#140
1'
1!
#141
0'
0!
#142
1'
1!
#143
0'
0!
#144
1'
1!
#145
0'
0!
#146
1'
1!
#147
0'
0!
#148
1'
1!
#149
0'
0!
#150
b1000 |
b1100 #"
b11 2"
b1 7"
b10001100 r
b110001 ("
b1000110000110001 h
b100001000110000110001 (
b100001000110000110001 "
b100001000110000110001 -
1'
1!
#151
0'
0!
#152
b1 :"
b11 5"
b110001 *"
b1100 &"
b1000 !"
b100001000110000110001 /
b1000110000110001 j
b10001100 t
1'
1!
#153
0'
0!
#154
1'
1!
#155
0'
0!
#156
1'
1!
#157
0'
0!
#158
1'
1!
#159
0'
0!
#160
1'
1!
#161
0'
0!
#162
1'
1!
#163
0'
0!
#164
1'
1!
#165
0'
0!
#166
1'
1!
#167
0'
0!
#168
1'
1!
#169
0'
0!
#170
1'
1!
#171
0'
0!
#172
00"
09"
0p
0+"
b0 3
b0 7
b0 i
04
0k
1'
1!
b1 +
b1 %
b1 .
#173
0'
0!
#174
b0 G
b0 K
b0 P
b10 a
b100000 8
b100000 V
b0 [
b0 _
b0 d
b0 =
b0 A
b0 U
b0 !"
b1000 &"
b1000 t
b0 y
b0 }
b0 $"
b110 5"
b10 :"
b1000000000100001100010 /
b100001100010 j
b1100010 *"
b0 /"
b0 3"
b0 8"
b0 o
b0 s
b0 )"
1'
1!
#175
1{
1~
1'"
1v
0'
0!
#176
b100 :"
b1100 5"
b11000100 *"
b0 &"
b1 !"
b1000011000100 j
b10000 t
b100 a
b10000000001000011000100 /
b1000000 8
b1000000 V
1'
1!
#177
1z
1%"
1q
1u
0{
0~
1."
1l
0'"
0v
16"
1-"
0'
0!
#178
b1000 a
b10000000 8
b10000000 V
b10 !"
b1 &"
b100001 t
b1000 5"
b1000 :"
b100000000010000110001000 /
b10000110001000 j
b10001000 *"
1'
1!
#179
1H
1Q
1?
1C
11"
14"
1Z
1:
1;"
1,"
1b
1Y
0'
0!
#180
b1111 |
b1110 #"
b1001 2"
b1110 7"
b11111110 r
b10011110 ("
b1111111010011110 h
b100001111111010011110 (
b100001111111010011110 "
b100001111111010011110 -
b0 :"
b1 5"
b10000 *"
b11 &"
b100 !"
b100001100010000 j
b1000011 t
b0 a
b0 V
b1 R
b1000000000100001100010000 /
b100000000 8
b1 B
1'
1!
#181
0H
0Q
0z
0%"
0?
0C
0q
0u
0Z
0:
0."
0l
01"
04"
0b
0Y
06"
0-"
0;"
0,"
0'
0!
#182
b10 R
b1000000000 8
b10 B
b1000 !"
b110 &"
b10000110 t
b10 5"
b10000000001000011000100000 /
b1000011000100000 j
b100000 *"
1'
1!
#183
1\
1e
1>
1W
15
19
1n
10
1x
1m
1""
1w
0'
0!
#184
b100 5"
b1000000 *"
b1100 &"
b0 !"
b110001000000 j
b1100 t
b1 f
b1 V
b100 R
b100000000010000110001000000 /
b10000000001 8
b100 B
1'
1!
#185
0\
0e
0>
0W
05
09
0n
00
0x
0m
1{
1~
0""
0w
1'"
1v
0'
0!
#186
b1000 R
b1000 B
b10 f
b100000000010 8
b10 V
b1 !"
b1000 &"
b11000 t
b1000 5"
b1000000000100001100010000000 /
b1100010000000 j
b10000000 *"
1'
1!
#187
1z
1%"
1q
1u
1."
1l
1I
1L
16"
1-"
1S
1D
0'
0!
#188
b0 5"
b0 *"
b1 &"
b11 !"
b11000100000000 j
b110001 t
b100 f
b100 V
b0 R
b1 M
b10000000001000011000100000000 /
b1000000000100 8
b10000 B
1'
1!
#189
0z
0%"
0q
0u
0I
0L
0{
0~
0."
0l
0S
0D
0'"
0v
06"
0-"
0'
0!
#190
b10 M
b100000 B
b1000 f
b10000000001000 8
b1000 V
b110 !"
b10 &"
b100000000010000110001000000000 /
b110001000000000 j
b1100010 t
1'
1!
#191
1]
1`
1g
1X
0'
0!
#192
b100 &"
b1100 !"
b1100010000000000 j
b11000100 t
b0 f
b1 a
b10000 V
b100 M
b1000000000100001100010000000000 /
b100000000010000 8
b1000000 B
1'
1!
#193
1\
1e
1>
1W
15
19
1n
10
0]
0`
1x
1m
0g
0X
1""
1w
0'
0!
#194
b1000 M
b10000000 B
b10 a
b1 f
b1000000000100001 8
b100001 V
b1000 !"
b1000 &"
b10000000001000011000100000000000 /
b1000100000000000 j
b10001000 t
1'
1!
#195
10"
19"
1p
1+"
12
14
1k
1<
11
1{
1~
1F
1;
1'"
1v
1N
1E
0'
0!
#196
02
b1 :"
b1 *"
b0 &"
b1 !"
b1000000000001 j
b10000 t
b11 f
b100 a
b1000011 V
b0 M
b10000110001000000000001 /
b1000011 8
b0 B
1'
1!
#197
00"
09"
0\
0e
0p
0+"
0>
0W
04
0k
05
09
0<
01
0n
00
0F
0;
0x
0m
0{
0~
0N
0E
0""
0w
0'"
0v
0'
0!
#198
b1000 a
b110 f
b10000110 8
b10000110 V
b10 !"
b100000 t
b10 :"
b100001100010000000000010 /
b10000000000010 j
b10 *"
1'
1!
#199
1H
1Q
1?
1C
1Z
1:
1b
1Y
0'
0!
#200
b100 :"
b100 *"
b100 !"
b100000000000100 j
b1000000 t
b1100 f
b0 a
b1100 V
b1 R
b1000011000100000000000100 /
b100001100 8
b1 B
1'
1!
#201
0H
0Q
0?
0C
0Z
0:
1]
1`
0b
0Y
1g
1X
0'
0!
#202
b10 R
b10 B
b1 a
b1000 f
b1000011000 8
b11000 V
b1000 !"
b10000000 t
b1000 :"
b10000110001000000000001000 /
b1000000000001000 j
b1000 *"
1'
1!
#203
1\
1e
1>
1W
15
19
1n
10
11"
14"
1x
1m
1;"
1,"
1""
1w
0'
0!
#204
b0 :"
b1 5"
b10000 *"
b0 !"
b10000 j
b0 t
b1 f
b11 a
b110001 V
b100 R
b100001100010000000000010000 /
b10000110001 8
b100 B
1'
1!
#205
0\
0e
0>
0W
05
09
0n
00
0]
0`
0x
0m
01"
04"
0g
0X
0""
0w
0;"
0,"
0'
0!
#206
b1000 R
b1000 B
b110 a
b10 f
b100001100010 8
b1100010 V
b10 5"
b1000011000100000000000100000 /
b100000 j
b100000 *"
1'
1!
#207
1I
1L
1S
1D
0'
0!
#208
b100 5"
b1000000 j
b1000000 *"
b100 f
b1100 a
b11000100 V
b0 R
b1 M
b10000110001000000000001000000 /
b1000011000100 8
b10000 B
1'
1!
#209
1H
1Q
1?
1C
0I
0L
1Z
1:
0S
0D
1b
1Y
0'
0!
#210
b1 c
b111 |
b1 #"
b0 2"
b1011 7"
b10001 T
b1110001 r
b1011 ("
b10001 6
b111000100001011 h
b100010111000100001011 (
b100010111000100001011 "
b100010111000100001011 -
b10 M
b1 R
b100001 B
b1000 a
b1000 f
b10000110001000 8
b10001000 V
b1000 5"
b100001100010000000000010000000 /
b10000000 j
b10000000 *"
1'
1!
#211
1z
1%"
1q
1u
1."
1l
1]
1`
16"
1-"
1g
1X
0'
0!
#212
b0 5"
b0 *"
b1 &"
b100000000 j
b1 t
b0 f
b1 a
b10000 V
b11 R
b100 M
b1000011000100000000000100000000 /
b100001100010000 8
b1000011 B
1'
1!
#213
0H
0Q
0z
0%"
0?
0C
0q
0u
0Z
0:
0]
0`
0."
0l
0b
0Y
0g
0X
06"
0-"
0'
0!
#214
b1000 M
b110 R
b10000110 B
b10 a
b1000011000100000 8
b100000 V
b10 &"
b10000110001000000000001000000000 /
b1000000000 j
b10 t
1'
1!
#215
10"
19"
1p
1+"
12
14
1k
1<
11
1F
1;
1N
1E
0'
0!
#216
02
b1 :"
b1 *"
b100 &"
b10000000001 j
b100 t
b100 a
b1000000 V
b1100 R
b0 M
b1100010000000000010000000001 /
b110001000000 8
b1100 B
1'
1!
#217
00"
09"
0p
0+"
04
0k
0<
01
0F
0;
1I
1L
0N
0E
1S
1D
0'
0!
#218
b1 M
b1000 R
b11000 B
b1000 a
b1100010000000 8
b10000000 V
b1000 &"
b1000 t
b10 :"
b11000100000000000100000000010 /
b100000000010 j
b10 *"
1'
1!
#219
1H
1Q
1?
1C
1{
1~
1Z
1:
1'"
1v
1b
1Y
0'
0!
#220
b100 :"
b100 *"
b0 &"
b1 !"
b1000000000100 j
b10000 t
b0 a
b0 V
b1 R
b11 M
b110001000000000001000000000100 /
b11000100000000 8
b110001 B
1'
1!
#221
0H
0Q
0?
0C
0I
0L
0Z
0:
0{
0~
0S
0D
0b
0Y
0'"
0v
0'
0!
#222
b110 M
b10 R
b110001000000000 8
b1100010 B
b10 !"
b100000 t
b1000 :"
b1100010000000000010000000001000 /
b10000000001000 j
b1000 *"
1'
1!
#223
11"
14"
1;"
1,"
0'
0!
