Digitales2/Tarea5/Tarea5AndresAlvaradoB30316/synth.v
`include "vlib/standar_lib.v"
/* Generated by Yosys 0.7 (git sha1 61f6811, gcc 6.2.0-10 -O2 -fdebug-prefix-map=/build/yosys-0DEyT5/yosys-0.7=. -fstack-protector-strong -fPIC -Os) */

(* top =  1  *)
(* src = "reg_desplazante.v:1" *)
module reg_desplazante(CLK, ENB, DIR, S_IN, MODO, D, Q, S_OUT);
  (* src = "reg_desplazante.v:12" *)
  wire [3:0] _000_;
  (* src = "reg_desplazante.v:12" *)
  wire _001_;
  wire _002_;
  wire _003_;
  wire _004_;
  wire _005_;
  wire _006_;
  wire _007_;
  wire _008_;
  wire _009_;
  wire _010_;
  wire _011_;
  wire _012_;
  wire _013_;
  wire _014_;
  wire _015_;
  wire _016_;
  wire _017_;
  wire _018_;
  wire _019_;
  wire _020_;
  wire _021_;
  wire _022_;
  wire _023_;
  wire _024_;
  wire _025_;
  wire _026_;
  wire _027_;
  wire _028_;
  wire _029_;
  wire _030_;
  wire _031_;
  wire _032_;
  wire _033_;
  wire _034_;
  wire _035_;
  wire _036_;
  wire _037_;
  wire _038_;
  wire _039_;
  wire _040_;
  wire _041_;
  wire _042_;
  wire _043_;
  wire _044_;
  wire _045_;
  wire _046_;
  wire _047_;
  wire _048_;
  wire _049_;
  wire _050_;
  wire _051_;
  wire _052_;
  wire _053_;
  wire _054_;
  wire _055_;
  wire _056_;
  wire _057_;
  wire _058_;
  wire _059_;
  wire _060_;
  wire _061_;
  wire _062_;
  (* src = "reg_desplazante.v:2" *)
  input CLK;
  (* src = "reg_desplazante.v:7" *)
  input [3:0] D;
  (* src = "reg_desplazante.v:4" *)
  input DIR;
  (* src = "reg_desplazante.v:3" *)
  input ENB;
  (* src = "reg_desplazante.v:6" *)
  input [1:0] MODO;
  (* src = "reg_desplazante.v:8" *)
  output [3:0] Q;
  (* src = "reg_desplazante.v:5" *)
  input S_IN;
  (* src = "reg_desplazante.v:9" *)
  output S_OUT;
  NAND _063_ (
    .A(MODO[1]),
    .B(MODO[0]),
    .Y(_002_)
  );
  NAND _064_ (
    .A(_002_),
    .B(ENB),
    .Y(_003_)
  );
  NOT _065_ (
    .A(_003_),
    .Y(_004_)
  );
  NOR _066_ (
    .A(_004_),
    .B(Q[0]),
    .Y(_005_)
  );
  NOT _067_ (
    .A(MODO[0]),
    .Y(_006_)
  );
  NOT _068_ (
    .A(MODO[1]),
    .Y(_007_)
  );
  NAND _069_ (
    .A(_007_),
    .B(_006_),
    .Y(_008_)
  );
  NAND _070_ (
    .A(DIR),
    .B(Q[1]),
    .Y(_009_)
  );
  NOT _071_ (
    .A(_009_),
    .Y(_010_)
  );
  NOT _072_ (
    .A(S_IN),
    .Y(_011_)
  );
  NOR _073_ (
    .A(_011_),
    .B(DIR),
    .Y(_012_)
  );
  NOR _074_ (
    .A(_012_),
    .B(_010_),
    .Y(_013_)
  );
  NOR _075_ (
    .A(_013_),
    .B(_008_),
    .Y(_014_)
  );
  NOR _076_ (
    .A(MODO[1]),
    .B(_006_),
    .Y(_015_)
  );
  NOT _077_ (
    .A(DIR),
    .Y(_016_)
  );
  NAND _078_ (
    .A(_016_),
    .B(Q[3]),
    .Y(_017_)
  );
  NAND _079_ (
    .A(_017_),
    .B(_009_),
    .Y(_018_)
  );
  NAND _080_ (
    .A(_018_),
    .B(_015_),
    .Y(_019_)
  );
  NOT _081_ (
    .A(D[0]),
    .Y(_020_)
  );
  NAND _082_ (
    .A(MODO[1]),
    .B(_006_),
    .Y(_021_)
  );
  NOR _083_ (
    .A(_021_),
    .B(_020_),
    .Y(_022_)
  );
  NOR _084_ (
    .A(_022_),
    .B(_003_),
    .Y(_023_)
  );
  NAND _085_ (
    .A(_023_),
    .B(_019_),
    .Y(_024_)
  );
  NOR _086_ (
    .A(_024_),
    .B(_014_),
    .Y(_025_)
  );
  NOR _087_ (
    .A(_025_),
    .B(_005_),
    .Y(_000_[0])
  );
  NAND _088_ (
    .A(_003_),
    .B(Q[1]),
    .Y(_026_)
  );
  NOR _089_ (
    .A(_007_),
    .B(MODO[0]),
    .Y(_027_)
  );
  NAND _090_ (
    .A(_027_),
    .B(D[1]),
    .Y(_028_)
  );
  NOT _091_ (
    .A(Q[2]),
    .Y(_029_)
  );
  NAND _092_ (
    .A(_029_),
    .B(DIR),
    .Y(_030_)
  );
  NOR _093_ (
    .A(Q[0]),
    .B(DIR),
    .Y(_031_)
  );
  NOR _094_ (
    .A(_031_),
    .B(MODO[1]),
    .Y(_032_)
  );
  NAND _095_ (
    .A(_032_),
    .B(_030_),
    .Y(_033_)
  );
  NAND _096_ (
    .A(_033_),
    .B(_028_),
    .Y(_034_)
  );
  NAND _097_ (
    .A(_034_),
    .B(ENB),
    .Y(_035_)
  );
  NAND _098_ (
    .A(_035_),
    .B(_026_),
    .Y(_000_[1])
  );
  NAND _099_ (
    .A(_003_),
    .B(Q[2]),
    .Y(_036_)
  );
  NAND _100_ (
    .A(_027_),
    .B(D[2]),
    .Y(_037_)
  );
  NOR _101_ (
    .A(_016_),
    .B(Q[3]),
    .Y(_038_)
  );
  NOR _102_ (
    .A(DIR),
    .B(Q[1]),
    .Y(_039_)
  );
  NOR _103_ (
    .A(_039_),
    .B(_038_),
    .Y(_040_)
  );
  NAND _104_ (
    .A(_040_),
    .B(_007_),
    .Y(_041_)
  );
  NAND _105_ (
    .A(_041_),
    .B(_037_),
    .Y(_042_)
  );
  NAND _106_ (
    .A(_042_),
    .B(ENB),
    .Y(_043_)
  );
  NAND _107_ (
    .A(_043_),
    .B(_036_),
    .Y(_000_[2])
  );
  NOR _108_ (
    .A(_004_),
    .B(Q[3]),
    .Y(_044_)
  );
  NOR _109_ (
    .A(_029_),
    .B(DIR),
    .Y(_045_)
  );
  NOR _110_ (
    .A(_011_),
    .B(_016_),
    .Y(_046_)
  );
  NOR _111_ (
    .A(_046_),
    .B(_045_),
    .Y(_047_)
  );
  NOR _112_ (
    .A(_047_),
    .B(_008_),
    .Y(_048_)
  );
  NAND _113_ (
    .A(Q[2]),
    .B(_016_),
    .Y(_049_)
  );
  NAND _114_ (
    .A(Q[0]),
    .B(DIR),
    .Y(_050_)
  );
  NAND _115_ (
    .A(_050_),
    .B(_049_),
    .Y(_051_)
  );
  NAND _116_ (
    .A(_051_),
    .B(_015_),
    .Y(_052_)
  );
  NOT _117_ (
    .A(D[3]),
    .Y(_053_)
  );
  NOR _118_ (
    .A(_021_),
    .B(_053_),
    .Y(_054_)
  );
  NOR _119_ (
    .A(_054_),
    .B(_003_),
    .Y(_055_)
  );
  NAND _120_ (
    .A(_055_),
    .B(_052_),
    .Y(_056_)
  );
  NOR _121_ (
    .A(_056_),
    .B(_048_),
    .Y(_057_)
  );
  NOR _122_ (
    .A(_057_),
    .B(_044_),
    .Y(_000_[3])
  );
  NAND _123_ (
    .A(_003_),
    .B(S_OUT),
    .Y(_058_)
  );
  NAND _124_ (
    .A(_050_),
    .B(_017_),
    .Y(_059_)
  );
  NOT _125_ (
    .A(ENB),
    .Y(_060_)
  );
  NOR _126_ (
    .A(_008_),
    .B(_060_),
    .Y(_061_)
  );
  NAND _127_ (
    .A(_061_),
    .B(_059_),
    .Y(_062_)
  );
  NAND _128_ (
    .A(_062_),
    .B(_058_),
    .Y(_001_)
  );
  DFF _129_ (
    .C(CLK),
    .D(_000_[0]),
    .Q(Q[0])
  );
  DFF _130_ (
    .C(CLK),
    .D(_000_[1]),
    .Q(Q[1])
  );
  DFF _131_ (
    .C(CLK),
    .D(_000_[2]),
    .Q(Q[2])
  );
  DFF _132_ (
    .C(CLK),
    .D(_000_[3]),
    .Q(Q[3])
  );
  DFF _133_ (
    .C(CLK),
    .D(_001_),
    .Q(S_OUT)
  );
endmodule

Digitales2/Proyecto/misc/Memory/Memory.v
module Memory
	(
	//inputs
	input wire [7:0] DATA_IN,
	input wire 	    CLK,
	input wire 	    RESET,
	input wire		WRITE,
	input wire		READ,
	//outputs
	output reg [7:0] DATA_OUT,
	output reg		almost_Full,
	output reg		almost_Empty,	
	output reg		errNoData,
	output reg		errOverflow,
	input wire		Valid
	);

    reg [7:0] 	    Memory[8];
	reg	[2:0]		indexW;
	reg	[2:0]		indexR;
	integer			positionR;
	integer			positionW;
	integer			index;
			

	always @(posedge CLK)
		begin
			if(RESET)
				begin
					for(index = 0; index <9; index = index+1)
					Memory[index] <= index;
					errNoData <= 0;
					errOverflow <= 0;
					positionR <= 0;
					positionW  <= 0;
					indexR <= 0;
					indexW <= 0;
				end
		end


	always @(posedge CLK)
		begin
			if(READ)
				begin
					DATA_OUT <= Memory[indexR];
					positionR <= positionR + 1;
					if(indexR == 8)
						begin
							indexR <= 0;
						end
					else
						begin
							if(indexR < 3)
									begin
										almost_Empty <= 1;
									end
								else
									begin
										almost_Empty <= 0;
									end
							indexR <= indexR + 1;
						end
				end
			if(WRITE)
				begin
					Memory[indexW] <= DATA_IN;
					positionW <= positionW + 1;
						if(indexW == 8)
							begin
								indexW <= 0;
							end
						else
							begin
								if(indexW > 6)
									begin
										almost_Full <= 1;
									end
								else
									begin
										almost_Full <= 0;
									end
								indexW <= indexW + 1;
							end
				end
			if(positionR > positionW)
				begin
					errNoData <= 1;
				end
			if(positionW > (positionR + 8))
				begin
					errOverflow <= 1;
				end

		end



endmodule

Digitales2/Proyecto/misc/Memory/tester.v

module tester
	(
	output reg [7:0] DATA_IN,
	output reg 	    CLK,
	output reg 	    RESET,
	output reg		WRITE,
	output reg		READ,
	output reg		BIG,
	output reg		Valid
   );

   	initial
    	begin
			CLK = 1;
			BIG = 1;
			Valid = 0;
			RESET = 0;
			WRITE = 0;
			READ = 0;
			@(posedge CLK)
			RESET = 1;
			@(posedge CLK)
			@(posedge CLK)
			RESET = 0;
			@(posedge CLK)
			DATA_IN <= 8'hFF;
			@(posedge CLK)
			WRITE <= 1;
			Valid <= 1;
			DATA_IN <= 8'hAA;
			@(posedge CLK)
			DATA_IN <= 8'hBB;
			@(posedge CLK)
			DATA_IN <= 8'hCC;
			@(posedge CLK)
			DATA_IN <= 8'hDD;
			READ <= 1;
			@(posedge CLK)
			DATA_IN <= 8'hEE;
			@(posedge CLK)
			READ <= 0;
			@(posedge CLK)
			@(posedge CLK)
			@(posedge CLK)
			READ <= 1;
			DATA_IN <= 8'b10100110;
			@(posedge CLK)
			DATA_IN <= 8'b00111001;
			@(posedge CLK)
			DATA_IN <= 8'b10101000;
			@(posedge CLK)
			READ <= 0;
			DATA_IN <= 8'b11111001;
			@(posedge CLK)
			DATA_IN <= 8'b01001111;
			@(posedge CLK)
			@(posedge CLK)
			@(posedge CLK)
			@(posedge CLK)
			@(posedge CLK)
			@(posedge CLK)
			@(posedge CLK)
			READ <= 1;
			DATA_IN <= 8'b11111001;
			@(posedge CLK)
			DATA_IN <= 8'b11111101;
			@(posedge CLK)
			DATA_IN <= 8'b11111111;
			@(posedge CLK)
			DATA_IN <= 8'b11110000;
			@(posedge CLK)
			@(posedge CLK)
			@(posedge CLK)
			@(posedge CLK)
			WRITE <= 0;
		end

   always
     begin
	#1 CLK <= ~CLK;
     end

endmodule

Digitales2/Proyecto/misc/Memory/test_bench.v
`timescale 1ns/100ps

`include "Memory.v"
`include "tester.v"
//`include "synth.v"

module testbench ();

   //Se definen inputs:
   wire CLK;
   wire [7:0] DATA_IN;
   wire Valid;
   wire [7:0] DATA_OUT;

   //Se definen outputs:
   wire       DATA_OUT0, DATA_OUT1, wRESET, WRITE, READ, BIG;

   tester prob
     (
      .CLK(CLK),
      .DATA_IN(DATA_IN),
      .RESET(wRESET),
      .WRITE(WRITE),
      .READ(READ),
      .BIG(BIG),
      .Valid(Valid)
      );

   Memory uut_cond
     (
      .DATA_IN(DATA_IN),
      .CLK(CLK),
      .RESET(wRESET),
      .WRITE(WRITE),
      .READ(READ),
      .Valid(Valid)
      );

   /*parallel_serial uut_estr
     (
      .CLK(CLK),
      .DATA_IN(DATA_IN),
      .RESET(wRESET),
      .DATA_OUT(DATA_OUT1)
      );
*/
   initial
     begin
	//For GTKWave usage.
	$dumpfile("simulation.vcd");
	$dumpvars();
	#1000 $finish();
     end

endmodule

Digitales2/Proyecto/misc/Memory/simulation.vcd
$date
	Tue Jul  3 21:03:23 2018
$end
$version
	Icarus Verilog
$end
$timescale
	100ps
$end
$scope module testbench $end
$var wire 1 ! wRESET $end
$var wire 1 " WRITE $end
$var wire 1 # Valid $end
$var wire 1 $ READ $end
$var wire 8 % DATA_IN [7:0] $end
$var wire 1 & CLK $end
$var wire 1 ' BIG $end
$scope module prob $end
$var reg 1 ' BIG $end
$var reg 1 & CLK $end
$var reg 8 ( DATA_IN [7:0] $end
$var reg 1 $ READ $end
$var reg 1 ! RESET $end
$var reg 1 # Valid $end
$var reg 1 " WRITE $end
$upscope $end
$scope module uut_cond $end
$var wire 1 & CLK $end
$var wire 8 ) DATA_IN [7:0] $end
$var wire 1 $ READ $end
$var wire 1 ! RESET $end
$var wire 1 # Valid $end
$var wire 1 " WRITE $end
$var reg 8 * DATA_OUT [7:0] $end
$var reg 1 + almost_Empty $end
$var reg 1 , almost_Full $end
$var reg 1 - errNoData $end
$var reg 1 . errOverflow $end
$var reg 3 / indexR [2:0] $end
$var reg 3 0 indexW [2:0] $end
$var integer 32 1 index [31:0] $end
$var integer 32 2 positionR [31:0] $end
$var integer 32 3 positionW [31:0] $end
$upscope $end
$upscope $end
$enddefinitions $end
#0
$dumpvars
bx 3
bx 2
bx 1
bx 0
bx /
x.
x-
x,
x+
bx *
bx )
bx (
1'
1&
bx %
0$
0#
0"
0!
$end
#10
0&
#20
1!
1&
#30
0&
#40
b0 0
b0 /
b0 3
b0 2
0.
0-
b1001 1
1&
#50
0&
#60
0!
b1001 1
1&
#70
0&
#80
b11111111 %
b11111111 (
b11111111 )
1&
#90
0&
#100
b10101010 %
b10101010 (
b10101010 )
1#
1"
1&
#110
0&
#120
b1 0
0,
b1 3
b10111011 %
b10111011 (
b10111011 )
1&
#130
0&
#140
b11001100 %
b11001100 (
b11001100 )
b10 0
b10 3
1&
#150
0&
#160
b11 0
b11 3
1$
b11011101 %
b11011101 (
b11011101 )
1&
#170
0&
#180
b11101110 %
b11101110 (
b11101110 )
b100 0
b100 3
b1 /
1+
b1 2
b10101010 *
1&
#190
0&
#200
b101 0
b101 3
b10 /
b10 2
b10111011 *
0$
1&
#210
0&
#220
b110 0
b110 3
1&
#230
0&
#240
b111 0
b111 3
1&
#250
0&
#260
b10100110 %
b10100110 (
b10100110 )
1$
b0 0
1,
b1000 3
1&
#270
0&
#280
b1 0
0,
b1001 3
b11 /
b11 2
b11001100 *
b111001 %
b111001 (
b111001 )
1&
#290
0&
#300
b10101000 %
b10101000 (
b10101000 )
b10 0
b1010 3
b100 /
0+
b100 2
b11011101 *
1&
#310
0&
#320
b11 0
b1011 3
b101 /
b101 2
b11101110 *
b11111001 %
b11111001 (
b11111001 )
0$
1&
#330
0&
#340
b1001111 %
b1001111 (
b1001111 )
b100 0
b1100 3
1&
#350
0&
#360
b101 0
b1101 3
1&
#370
0&
#380
b110 0
b1110 3
1&
#390
0&
#400
1.
b111 0
b1111 3
1&
#410
0&
#420
b0 0
1,
b10000 3
1&
#430
0&
#440
b1 0
0,
b10001 3
1&
#450
0&
#460
b10 0
b10010 3
1&
#470
0&
#480
b11 0
b10011 3
b11111001 %
b11111001 (
b11111001 )
1$
1&
#490
0&
#500
b11111101 %
b11111101 (
b11111101 )
b100 0
b10100 3
b110 /
b110 2
b1001111 *
1&
#510
0&
#520
b101 0
b10101 3
b111 /
b111 2
b11111111 %
b11111111 (
b11111111 )
1&
#530
0&
#540
b11110000 %
b11110000 (
b11110000 )
b110 0
b10110 3
b0 /
b1000 2
1&
#550
0&
#560
b111 0
b10111 3
b1 /
1+
b1001 2
1&
#570
0&
#580
b0 0
1,
b11000 3
b10 /
b1010 2
1&
#590
0&
#600
b1 0
0,
b11001 3
b11 /
b1011 2
1&
#610
0&
#620
0"
b10 0
b11010 3
b100 /
0+
b1100 2
b11111001 *
1&
#630
0&
#640
b101 /
b1101 2
b11111101 *
1&
#650
0&
#660
b110 /
b1110 2
b11111111 *
1&
#670
0&
#680
b111 /
b1111 2
b11110000 *
1&
#690
0&
#700
b0 /
b10000 2
1&
#710
0&
#720
b1 /
1+
b10001 2
1&
#730
0&
#740
b10 /
b10010 2
1&
#750
0&
#760
b11 /
b10011 2
b1001111 *
1&
#770
0&
#780
b100 /
0+
b10100 2
b11111001 *
1&
#790
0&
#800
b101 /
b10101 2
b11111101 *
1&
#810
0&
#820
b110 /
b10110 2
b11111111 *
1&
#830
0&
#840
b111 /
b10111 2
b11110000 *
1&
#850
0&
#860
b0 /
b11000 2
1&
#870
0&
#880
b1 /
1+
b11001 2
1&
#890
0&
#900
b10 /
b11010 2
1&
#910
0&
#920
b11 /
b11011 2
b1001111 *
1&
#930
0&
#940
1-
b100 /
0+
b11100 2
b11111001 *
1&
#950
0&
#960
b101 /
b11101 2
b11111101 *
1&
#970
0&
#980
b110 /
b11110 2
b11111111 *
1&
#990
0&
#1000
b111 /
b11111 2
b11110000 *
1&
#1010
0&
#1020
b0 /
b100000 2
1&
#1030
0&
#1040
b1 /
1+
b100001 2
1&
#1050
0&
#1060
b10 /
b100010 2
1&
#1070
0&
#1080
b11 /
b100011 2
b1001111 *
1&
#1090
0&
#1100
b100 /
0+
b100100 2
b11111001 *
1&
#1110
0&
#1120
b101 /
b100101 2
b11111101 *
1&
#1130
0&
#1140
b110 /
b100110 2
b11111111 *
1&
#1150
0&
#1160
b111 /
b100111 2
b11110000 *
1&
#1170
0&
#1180
b0 /
b101000 2
1&
#1190
0&
#1200
b1 /
1+
b101001 2
1&
#1210
0&
#1220
b10 /
b101010 2
1&
#1230
0&
#1240
b11 /
b101011 2
b1001111 *
1&
#1250
0&
#1260
b100 /
0+
b101100 2
b11111001 *
1&
#1270
0&
#1280
b101 /
b101101 2
b11111101 *
1&
#1290
0&
#1300
b110 /
b101110 2
b11111111 *
1&
#1310
0&
#1320
b111 /
b101111 2
b11110000 *
1&
#1330
0&
#1340
b0 /
b110000 2
1&
#1350
0&
#1360
b1 /
1+
b110001 2
1&
#1370
0&
#1380
b10 /
b110010 2
1&
#1390
0&
#1400
b11 /
b110011 2
b1001111 *
1&
#1410
0&
#1420
b100 /
0+
b110100 2
b11111001 *
1&
#1430
0&
#1440
b101 /
b110101 2
b11111101 *
1&
#1450
0&
#1460
b110 /
b110110 2
b11111111 *
1&
#1470
0&
#1480
b111 /
b110111 2
b11110000 *
1&
#1490
0&
#1500
b0 /
b111000 2
1&
#1510
0&
#1520
b1 /
1+
b111001 2
1&
#1530
0&
#1540
b10 /
b111010 2
1&
#1550
0&
#1560
b11 /
b111011 2
b1001111 *
1&
#1570
0&
#1580
b100 /
0+
b111100 2
b11111001 *
1&
#1590
0&
#1600
b101 /
b111101 2
b11111101 *
1&
#1610
0&
#1620
b110 /
b111110 2
b11111111 *
1&
#1630
0&
#1640
b111 /
b111111 2
b11110000 *
1&
#1650
0&
#1660
b0 /
b1000000 2
1&
#1670
0&
#1680
b1 /
1+
b1000001 2
1&
#1690
0&
#1700
b10 /
b1000010 2
1&
#1710
0&
#1720
b11 /
b1000011 2
b1001111 *
1&
#1730
0&
#1740
b100 /
0+
b1000100 2
b11111001 *
1&
#1750
0&
#1760
b101 /
b1000101 2
b11111101 *
1&
#1770
0&
#1780
b110 /
b1000110 2
b11111111 *
1&
#1790
0&
#1800
b111 /
b1000111 2
b11110000 *
1&
#1810
0&
#1820
b0 /
b1001000 2
1&
#1830
0&
#1840
b1 /
1+
b1001001 2
1&
#1850
0&
#1860
b10 /
b1001010 2
1&
#1870
0&
#1880
b11 /
b1001011 2
b1001111 *
1&
#1890
0&
#1900
b100 /
0+
b1001100 2
b11111001 *
1&
#1910
0&
#1920
b101 /
b1001101 2
b11111101 *
1&
#1930
0&
#1940
b110 /
b1001110 2
b11111111 *
1&
#1950
0&
#1960
b111 /
b1001111 2
b11110000 *
1&
#1970
0&
#1980
b0 /
b1010000 2
1&
#1990
0&
#2000
b1 /
1+
b1010001 2
1&
#2010
0&
#2020
b10 /
b1010010 2
1&
#2030
0&
#2040
b11 /
b1010011 2
b1001111 *
1&
#2050
0&
#2060
b100 /
0+
b1010100 2
b11111001 *
1&
#2070
0&
#2080
b101 /
b1010101 2
b11111101 *
1&
#2090
0&
#2100
b110 /
b1010110 2
b11111111 *
1&
#2110
0&
#2120
b111 /
b1010111 2
b11110000 *
1&
#2130
0&
#2140
b0 /
b1011000 2
1&
#2150
0&
#2160
b1 /
1+
b1011001 2
1&
#2170
0&
#2180
b10 /
b1011010 2
1&
#2190
0&
#2200
b11 /
b1011011 2
b1001111 *
1&
#2210
0&
#2220
b100 /
0+
b1011100 2
b11111001 *
1&
#2230
0&
#2240
b101 /
b1011101 2
b11111101 *
1&
#2250
0&
#2260
b110 /
b1011110 2
b11111111 *
1&
#2270
0&
#2280
b111 /
b1011111 2
b11110000 *
1&
#2290
0&
#2300
b0 /
b1100000 2
1&
#2310
0&
#2320
b1 /
1+
b1100001 2
1&
#2330
0&
#2340
b10 /
b1100010 2
1&
#2350
0&
#2360
b11 /
b1100011 2
b1001111 *
1&
#2370
0&
#2380
b100 /
0+
b1100100 2
b11111001 *
1&
#2390
0&
#2400
b101 /
b1100101 2
b11111101 *
1&
#2410
0&
#2420
b110 /
b1100110 2
b11111111 *
1&
#2430
0&
#2440
b111 /
b1100111 2
b11110000 *
1&
#2450
0&
#2460
b0 /
b1101000 2
1&
#2470
0&
#2480
b1 /
1+
b1101001 2
1&
#2490
0&
#2500
b10 /
b1101010 2
1&
#2510
0&
#2520
b11 /
b1101011 2
b1001111 *
1&
#2530
0&
#2540
b100 /
0+
b1101100 2
b11111001 *
1&
#2550
0&
#2560
b101 /
b1101101 2
b11111101 *
1&
#2570
0&
#2580
b110 /
b1101110 2
b11111111 *
1&
#2590
0&
#2600
b111 /
b1101111 2
b11110000 *
1&
#2610
0&
#2620
b0 /
b1110000 2
1&
#2630
0&
#2640
b1 /
1+
b1110001 2
1&
#2650
0&
#2660
b10 /
b1110010 2
1&
#2670
0&
#2680
b11 /
b1110011 2
b1001111 *
1&
#2690
0&
#2700
b100 /
0+
b1110100 2
b11111001 *
1&
#2710
0&
#2720
b101 /
b1110101 2
b11111101 *
1&
#2730
0&
#2740
b110 /
b1110110 2
b11111111 *
1&
#2750
0&
#2760
b111 /
b1110111 2
b11110000 *
1&
#2770
0&
#2780
b0 /
b1111000 2
1&
#2790
0&
#2800
b1 /
1+
b1111001 2
1&
#2810
0&
#2820
b10 /
b1111010 2
1&
#2830
0&
#2840
b11 /
b1111011 2
b1001111 *
1&
#2850
0&
#2860
b100 /
0+
b1111100 2
b11111001 *
1&
#2870
0&
#2880
b101 /
b1111101 2
b11111101 *
1&
#2890
0&
#2900
b110 /
b1111110 2
b11111111 *
1&
#2910
0&
#2920
b111 /
b1111111 2
b11110000 *
1&
#2930
0&
#2940
b0 /
b10000000 2
1&
#2950
0&
#2960
b1 /
1+
b10000001 2
1&
#2970
0&
#2980
b10 /
b10000010 2
1&
#2990
0&
#3000
b11 /
b10000011 2
b1001111 *
1&
#3010
0&
#3020
b100 /
0+
b10000100 2
b11111001 *
1&
#3030
0&
#3040
b101 /
b10000101 2
b11111101 *
1&
#3050
0&
#3060
b110 /
b10000110 2
b11111111 *
1&
#3070
0&
#3080
b111 /
b10000111 2
b11110000 *
1&
#3090
0&
#3100
b0 /
b10001000 2
1&
#3110
0&
#3120
b1 /
1+
b10001001 2
1&
#3130
0&
#3140
b10 /
b10001010 2
1&
#3150
0&
#3160
b11 /
b10001011 2
b1001111 *
1&
#3170
0&
#3180
b100 /
0+
b10001100 2
b11111001 *
1&
#3190
0&
#3200
b101 /
b10001101 2
b11111101 *
1&
#3210
0&
#3220
b110 /
b10001110 2
b11111111 *
1&
#3230
0&
#3240
b111 /
b10001111 2
b11110000 *
1&
#3250
0&
#3260
b0 /
b10010000 2
1&
#3270
0&
#3280
b1 /
1+
b10010001 2
1&
#3290
0&
#3300
b10 /
b10010010 2
1&
#3310
0&
#3320
b11 /
b10010011 2
b1001111 *
1&
#3330
0&
#3340
b100 /
0+
b10010100 2
b11111001 *
1&
#3350
0&
#3360
b101 /
b10010101 2
b11111101 *
1&
#3370
0&
#3380
b110 /
b10010110 2
b11111111 *
1&
#3390
0&
#3400
b111 /
b10010111 2
b11110000 *
1&
#3410
0&
#3420
b0 /
b10011000 2
1&
#3430
0&
#3440
b1 /
1+
b10011001 2
1&
#3450
0&
#3460
b10 /
b10011010 2
1&
#3470
0&
#3480
b11 /
b10011011 2
b1001111 *
1&
#3490
0&
#3500
b100 /
0+
b10011100 2
b11111001 *
1&
#3510
0&
#3520
b101 /
b10011101 2
b11111101 *
1&
#3530
0&
#3540
b110 /
b10011110 2
b11111111 *
1&
#3550
0&
#3560
b111 /
b10011111 2
b11110000 *
1&
#3570
0&
#3580
b0 /
b10100000 2
1&
#3590
0&
#3600
b1 /
1+
b10100001 2
1&
#3610
0&
#3620
b10 /
b10100010 2
1&
#3630
0&
#3640
b11 /
b10100011 2
b1001111 *
1&
#3650
0&
#3660
b100 /
0+
b10100100 2
b11111001 *
1&
#3670
0&
#3680
b101 /
b10100101 2
b11111101 *
1&
#3690
0&
#3700
b110 /
b10100110 2
b11111111 *
1&
#3710
0&
#3720
b111 /
b10100111 2
b11110000 *
1&
#3730
0&
#3740
b0 /
b10101000 2
1&
#3750
0&
#3760
b1 /
1+
b10101001 2
1&
#3770
0&
#3780
b10 /
b10101010 2
1&
#3790
0&
#3800
b11 /
b10101011 2
b1001111 *
1&
#3810
0&
#3820
b100 /
0+
b10101100 2
b11111001 *
1&
#3830
0&
#3840
b101 /
b10101101 2
b11111101 *
1&
#3850
0&
#3860
b110 /
b10101110 2
b11111111 *
1&
#3870
0&
#3880
b111 /
b10101111 2
b11110000 *
1&
#3890
0&
#3900
b0 /
b10110000 2
1&
#3910
0&
#3920
b1 /
1+
b10110001 2
1&
#3930
0&
#3940
b10 /
b10110010 2
1&
#3950
0&
#3960
b11 /
b10110011 2
b1001111 *
1&
#3970
0&
#3980
b100 /
0+
b10110100 2
b11111001 *
1&
#3990
0&
#4000
b101 /
b10110101 2
b11111101 *
1&
#4010
0&
#4020
b110 /
b10110110 2
b11111111 *
1&
#4030
0&
#4040
b111 /
b10110111 2
b11110000 *
1&
#4050
0&
#4060
b0 /
b10111000 2
1&
#4070
0&
#4080
b1 /
1+
b10111001 2
1&
#4090
0&
#4100
b10 /
b10111010 2
1&
#4110
0&
#4120
b11 /
b10111011 2
b1001111 *
1&
#4130
0&
#4140
b100 /
0+
b10111100 2
b11111001 *
1&
#4150
0&
#4160
b101 /
b10111101 2
b11111101 *
1&
#4170
0&
#4180
b110 /
b10111110 2
b11111111 *
1&
#4190
0&
#4200
b111 /
b10111111 2
b11110000 *
1&
#4210
0&
#4220
b0 /
b11000000 2
1&
#4230
0&
#4240
b1 /
1+
b11000001 2
1&
#4250
0&
#4260
b10 /
b11000010 2
1&
#4270
0&
#4280
b11 /
b11000011 2
b1001111 *
1&
#4290
0&
#4300
b100 /
0+
b11000100 2
b11111001 *
1&
#4310
0&
#4320
b101 /
b11000101 2
b11111101 *
1&
#4330
0&
#4340
b110 /
b11000110 2
b11111111 *
1&
#4350
0&
#4360
b111 /
b11000111 2
b11110000 *
1&
#4370
0&
#4380
b0 /
b11001000 2
1&
#4390
0&
#4400
b1 /
1+
b11001001 2
1&
#4410
0&
#4420
b10 /
b11001010 2
1&
#4430
0&
#4440
b11 /
b11001011 2
b1001111 *
1&
#4450
0&
#4460
b100 /
0+
b11001100 2
b11111001 *
1&
#4470
0&
#4480
b101 /
b11001101 2
b11111101 *
1&
#4490
0&
#4500
b110 /
b11001110 2
b11111111 *
1&
#4510
0&
#4520
b111 /
b11001111 2
b11110000 *
1&
#4530
0&
#4540
b0 /
b11010000 2
1&
#4550
0&
#4560
b1 /
1+
b11010001 2
1&
#4570
0&
#4580
b10 /
b11010010 2
1&
#4590
0&
#4600
b11 /
b11010011 2
b1001111 *
1&
#4610
0&
#4620
b100 /
0+
b11010100 2
b11111001 *
1&
#4630
0&
#4640
b101 /
b11010101 2
b11111101 *
1&
#4650
0&
#4660
b110 /
b11010110 2
b11111111 *
1&
#4670
0&
#4680
b111 /
b11010111 2
b11110000 *
1&
#4690
0&
#4700
b0 /
b11011000 2
1&
#4710
0&
#4720
b1 /
1+
b11011001 2
1&
#4730
0&
#4740
b10 /
b11011010 2
1&
#4750
0&
#4760
b11 /
b11011011 2
b1001111 *
1&
#4770
0&
#4780
b100 /
0+
b11011100 2
b11111001 *
1&
#4790
0&
#4800
b101 /
b11011101 2
b11111101 *
1&
#4810
0&
#4820
b110 /
b11011110 2
b11111111 *
1&
#4830
0&
#4840
b111 /
b11011111 2
b11110000 *
1&
#4850
0&
#4860
b0 /
b11100000 2
1&
#4870
0&
#4880
b1 /
1+
b11100001 2
1&
#4890
0&
#4900
b10 /
b11100010 2
1&
#4910
0&
#4920
b11 /
b11100011 2
b1001111 *
1&
#4930
0&
#4940
b100 /
0+
b11100100 2
b11111001 *
1&
#4950
0&
#4960
b101 /
b11100101 2
b11111101 *
1&
#4970
0&
#4980
b110 /
b11100110 2
b11111111 *
1&
#4990
0&
#5000
b111 /
b11100111 2
b11110000 *
1&
#5010
0&
#5020
b0 /
b11101000 2
1&
#5030
0&
#5040
b1 /
1+
b11101001 2
1&
#5050
0&
#5060
b10 /
b11101010 2
1&
#5070
0&
#5080
b11 /
b11101011 2
b1001111 *
1&
#5090
0&
#5100
b100 /
0+
b11101100 2
b11111001 *
1&
#5110
0&
