Digitales2/Proyecto/misc/roundrobin/roundrobin.v
module roundrobin(	input reset,
		input [19:0] request,
		output reg [1:0] pop_id,
		input clk,
		input valid,
		input [3:0] empty,
		output reg read); 

	reg [1:0] mem1 [0:9];
	integer index;
	integer aux;
	integer count = 0;

	always @ (posedge clk) begin

		if (reset != 0) begin

			for (index = 0; index < 11; index = index + 1) begin

				mem1 [index] <= (request[index * 2] << 1) + request[index * 2 + 1];
			end

		end

		if (reset == 0 && valid) begin

			aux = mem1[count];

			if (count == 9)
				count <= 0;

			case (count)

				0:
					begin	
						if (empty[aux] == 0) begin
							pop_id <= mem1 [count];
							count = count + 1;
							read = 1;
						end
						else begin
							count = count + 1;
							read = 0;
						end
					end
				1:	
					begin
						if (empty[aux] == 0) begin
							pop_id <= mem1 [count];
							count = count + 1;
							read = 1;
						end
						else begin
							count = count + 1;
							read = 0;
						end
					end
				2:
					begin
						if (empty[aux] == 0) begin
							pop_id <= mem1 [count];
							count = count + 1;
							read = 1;
						end
						else begin
							count = count + 1;
							read = 0;
						end
					end
				3:
					begin	
						if (empty[aux] == 0) begin
							pop_id <= mem1 [count];
							count = count + 1;
							read = 1;
						end
						else begin
							count = count + 1;
							read = 0;
						end
					end
				4:
					begin	
						if (empty[aux] == 0) begin
							pop_id <= mem1 [count];
							count = count + 1;
							read = 1;
						end
						else begin
							count = count + 1;
							read = 0;
						end
					end
				5:
					begin
						if (empty[aux] == 0) begin
							pop_id <= mem1 [count];
							count = count + 1;
							read = 1;
						end
						else begin
							count = count + 1;
							read = 0;
						end
					end
				6:
					begin
						if (empty[aux] == 0) begin
							pop_id <= mem1 [count];
							count = count + 1;
							read = 1;
						end
						else begin
							count = count + 1;
							read = 0;
						end
					end
				7:
					begin
						if (empty[aux] == 0) begin
							pop_id <= mem1 [count];
							count = count + 1;
							read = 1;
						end
						else begin
							count = count + 1;
							read = 0;
						end
					end
				8:
					begin
						if (empty[aux] == 0) begin
							pop_id <= mem1 [count];
							count = count + 1;
							read = 1;
						end
						else begin
							count = count + 1;
							read = 0;
						end
					end	
				9:
					begin
						if (empty[aux] == 0) begin
							pop_id <= mem1 [count];
							count = count + 1;
							read = 1;
						end
						else begin
							count = count + 1;
							read = 0;
						end
					end
				default:
					begin
						count = count;
					end
			endcase

		end
	
	end

endmodule

Digitales2/Proyecto/misc/roundrobin/tester.v
module tester(reset, request, pop_id, clk, valid, empty, read);

output reg [19:0] request;
output reg clk;
output reg reset;
output reg [1:0] pop_id;
output reg [3:0] empty;
output reg valid;
output reg read;

   initial
     begin
	clk = 1;
	request = 20'b11001110000110111001;
	reset = 1;
	empty = 4'b0000;
	pop_id = 2'b00;
	valid = 1;
	read = 0;
	#4 reset = 0;
	#10 empty = 4'b1111;
	#40;
	$display ("mem1[0] = %b", roundrobin.mem1[0]);
	$display ("mem1[1] = %b", roundrobin.mem1[1]);
	$display ("mem1[2] = %b", roundrobin.mem1[2]);
	$display ("mem1[3] = %b", roundrobin.mem1[3]);
	$display ("mem1[4] = %b", roundrobin.mem1[4]);
	$display ("mem1[5] = %b", roundrobin.mem1[5]);
	$display ("mem1[6] = %b", roundrobin.mem1[6]);
	$display ("mem1[7] = %b", roundrobin.mem1[7]);
	$display ("mem1[8] = %b", roundrobin.mem1[8]);
	$display ("mem1[9] = %b", roundrobin.mem1[9]);
	#20 empty = 4'b0000;
	#100 $finish;
     end

   always
     begin
	#1 clk = ~clk;
     end

endmodule

Digitales2/Proyecto/misc/roundrobin/test_bench.v
`include "tester.v" // Agrega archivo de codigo
`include "roundrobin.v" // Agrega archivo de codigo


module test_bench();

	wire clk;
	wire [19:0] request;
	wire reset;
	wire valid;
	wire [1:0] pop_id;
	wire [3:0] empty;
	wire read;

  	tester probador (reset, request, pop_id, clk, valid, empty, read); 
  	roundrobin roundrobin (reset, request, pop_id, clk, valid, empty, read); 
	
  	initial
    		begin
      			$dumpfile("simulation.vcd");
      			$dumpvars;
    		end

endmodule

Digitales2/Proyecto/misc/roundrobin/simulation.vcd
$date
	Sat Jun 30 15:29:08 2018
$end
$version
	Icarus Verilog
$end
$timescale
	1s
$end
$scope module test_bench $end
$var wire 1 ! clk $end
$var wire 4 " empty [3:0] $end
$var wire 2 # pop_id [1:0] $end
$var wire 1 $ read $end
$var wire 20 % request [19:0] $end
$var wire 1 & reset $end
$var wire 1 ' valid $end
$scope module probador $end
$var reg 1 ( clk $end
$var reg 4 ) empty [3:0] $end
$var reg 2 * pop_id [1:0] $end
$var reg 1 + read $end
$var reg 20 , request [19:0] $end
$var reg 1 - reset $end
$var reg 1 . valid $end
$upscope $end
$scope module roundrobin $end
$var wire 1 ! clk $end
$var wire 4 / empty [3:0] $end
$var wire 20 0 request [19:0] $end
$var wire 1 & reset $end
$var wire 1 ' valid $end
$var integer 32 1 aux [31:0] $end
$var integer 32 2 count [31:0] $end
$var integer 32 3 index [31:0] $end
$var reg 2 4 pop_id [1:0] $end
$var reg 1 5 read $end
$upscope $end
$upscope $end
$enddefinitions $end
#0
$dumpvars
x5
bx 4
bx 3
b0 2
bx 1
b11001110000110111001 0
b0 /
1.
1-
b11001110000110111001 ,
0+
b0 *
b0 )
1(
1'
1&
b11001110000110111001 %
x$
bx #
b0 "
1!
$end
#1
0(
0!
#2
b1011 3
1(
1!
#3
0(
0!
#4
b10 4
bx0 #
15
b1 2
b10 1
1(
1!
0-
0&
#5
0(
0!
#6
b1 4
b0x #
b10 2
b1 1
1(
1!
#7
0(
0!
#8
b11 4
bx #
b11 2
b11 1
1(
1!
#9
0(
0!
#10
b1 4
b0x #
b100 2
b1 1
1(
1!
#11
0(
0!
#12
b10 4
bx0 #
b101 2
b10 1
1(
1!
#13
0(
0!
#14
05
0$
b110 2
b0 1
1(
1!
b1111 )
b1111 "
b1111 /
#15
0(
0!
#16
b111 2
b1 1
1(
1!
#17
0(
0!
#18
b1000 2
b11 1
1(
1!
#19
0(
0!
#20
b1001 2
b0 1
1(
1!
#21
0(
0!
#22
b0 2
b11 1
1(
1!
#23
0(
0!
#24
b1 2
b10 1
1(
1!
#25
0(
0!
#26
b10 2
b1 1
1(
1!
#27
0(
0!
#28
b11 2
b11 1
1(
1!
#29
0(
0!
#30
b100 2
b1 1
1(
1!
#31
0(
0!
#32
b101 2
b10 1
1(
1!
#33
0(
0!
#34
b110 2
b0 1
1(
1!
#35
0(
0!
#36
b111 2
b1 1
1(
1!
#37
0(
0!
#38
b1000 2
b11 1
1(
1!
#39
0(
0!
#40
b1001 2
b0 1
1(
1!
#41
0(
0!
#42
b0 2
b11 1
1(
1!
#43
0(
0!
#44
b1 2
b10 1
1(
1!
#45
0(
0!
#46
b10 2
b1 1
1(
1!
#47
0(
0!
#48
b11 2
b11 1
1(
1!
#49
0(
0!
#50
b100 2
b1 1
1(
1!
#51
0(
0!
#52
b101 2
b10 1
1(
1!
#53
0(
0!
#54
b110 2
b0 1
1(
1!
#55
0(
0!
#56
b111 2
b1 1
1(
1!
#57
0(
0!
#58
b1000 2
b11 1
1(
1!
#59
0(
0!
#60
b1001 2
b0 1
1(
1!
#61
0(
0!
#62
b0 2
b11 1
1(
1!
#63
0(
0!
#64
b1 2
b10 1
1(
1!
#65
0(
0!
#66
b10 2
b1 1
1(
1!
#67
0(
0!
#68
b11 2
b11 1
1(
1!
#69
0(
0!
#70
b100 2
b1 1
1(
1!
#71
0(
0!
#72
b101 2
b10 1
1(
1!
#73
0(
0!
#74
b0 4
b0 #
15
x$
b110 2
b0 1
1(
1!
b0 )
b0 "
b0 /
#75
0(
0!
#76
b1 4
b0x #
b111 2
b1 1
1(
1!
#77
0(
0!
#78
b11 4
bx #
b1000 2
b11 1
1(
1!
#79
0(
0!
#80
b0 4
b0 #
b1001 2
b0 1
1(
1!
#81
0(
0!
#82
b11 4
bx #
b0 2
b11 1
1(
1!
#83
0(
0!
#84
b10 4
bx0 #
b1 2
b10 1
1(
1!
#85
0(
0!
#86
b1 4
b0x #
b10 2
b1 1
1(
1!
#87
0(
0!
#88
b11 4
bx #
b11 2
b11 1
1(
1!
#89
0(
0!
#90
b1 4
b0x #
b100 2
b1 1
1(
1!
#91
0(
0!
#92
b10 4
bx0 #
b101 2
b10 1
1(
1!
#93
0(
0!
#94
b0 4
b0 #
b110 2
b0 1
1(
1!
#95
0(
0!
#96
b1 4
b0x #
b111 2
b1 1
1(
1!
#97
0(
0!
#98
b11 4
bx #
b1000 2
b11 1
1(
1!
#99
0(
0!
#100
b0 4
b0 #
b1001 2
b0 1
1(
1!
#101
0(
0!
#102
b11 4
bx #
b0 2
b11 1
1(
1!
#103
0(
0!
#104
b10 4
bx0 #
b1 2
b10 1
1(
1!
#105
0(
0!
#106
b1 4
b0x #
b10 2
b1 1
1(
1!
#107
0(
0!
#108
b11 4
bx #
b11 2
b11 1
1(
1!
#109
0(
0!
#110
b1 4
b0x #
b100 2
b1 1
1(
1!
#111
0(
0!
#112
b10 4
bx0 #
b101 2
b10 1
1(
1!
#113
0(
0!
#114
b0 4
b0 #
b110 2
b0 1
1(
1!
#115
0(
0!
#116
b1 4
b0x #
b111 2
b1 1
1(
1!
#117
0(
0!
#118
b11 4
bx #
b1000 2
b11 1
1(
1!
#119
0(
0!
#120
b0 4
b0 #
b1001 2
b0 1
1(
1!
#121
0(
0!
#122
b11 4
bx #
b0 2
b11 1
1(
1!
#123
0(
0!
#124
b10 4
bx0 #
b1 2
b10 1
1(
1!
#125
0(
0!
#126
b1 4
b0x #
b10 2
b1 1
1(
1!
#127
0(
0!
#128
b11 4
bx #
b11 2
b11 1
1(
1!
#129
0(
0!
#130
b1 4
b0x #
b100 2
b1 1
1(
1!
#131
0(
0!
#132
b10 4
bx0 #
b101 2
b10 1
1(
1!
#133
0(
0!
#134
b0 4
b0 #
b110 2
b0 1
1(
1!
#135
0(
0!
#136
b1 4
b0x #
b111 2
b1 1
1(
1!
#137
0(
0!
#138
b11 4
bx #
b1000 2
b11 1
1(
1!
#139
0(
0!
#140
b0 4
b0 #
b1001 2
b0 1
1(
1!
#141
0(
0!
#142
b11 4
bx #
b0 2
b11 1
1(
1!
#143
0(
0!
#144
b10 4
bx0 #
b1 2
b10 1
1(
1!
#145
0(
0!
#146
b1 4
b0x #
b10 2
b1 1
1(
1!
#147
0(
0!
#148
b11 4
bx #
b11 2
b11 1
1(
1!
#149
0(
0!
#150
b1 4
b0x #
b100 2
b1 1
1(
1!
#151
0(
0!
#152
b10 4
bx0 #
b101 2
b10 1
1(
1!
#153
0(
0!
#154
b0 4
b0 #
b110 2
b0 1
1(
1!
#155
0(
0!
#156
b1 4
b0x #
b111 2
b1 1
1(
1!
#157
0(
0!
#158
b11 4
bx #
b1000 2
b11 1
1(
1!
#159
0(
0!
#160
b0 4
b0 #
b1001 2
b0 1
1(
1!
#161
0(
0!
#162
b11 4
bx #
b0 2
b11 1
1(
1!
#163
0(
0!
#164
b10 4
bx0 #
b1 2
b10 1
1(
1!
#165
0(
0!
#166
b1 4
b0x #
b10 2
b1 1
1(
1!
#167
0(
0!
#168
b11 4
bx #
b11 2
b11 1
1(
1!
#169
0(
0!
#170
b1 4
b0x #
b100 2
b1 1
1(
1!
#171
0(
0!
#172
b10 4
bx0 #
b101 2
b10 1
1(
1!
#173
0(
0!
#174
b0 4
b0 #
b110 2
b0 1
1(
1!
