Digitales2/Tarea5/Tarea5AndresAlvaradoB30316/synth.v
`include "vlib/standar_lib.v"
/* Generated by Yosys 0.7 (git sha1 61f6811, gcc 6.2.0-10 -O2 -fdebug-prefix-map=/build/yosys-0DEyT5/yosys-0.7=. -fstack-protector-strong -fPIC -Os) */

(* top =  1  *)
(* src = "reg_desplazante.v:1" *)
module reg_desplazante(CLK, ENB, DIR, S_IN, MODO, D, Q, S_OUT);
  (* src = "reg_desplazante.v:12" *)
  wire [3:0] _000_;
  (* src = "reg_desplazante.v:12" *)
  wire _001_;
  wire _002_;
  wire _003_;
  wire _004_;
  wire _005_;
  wire _006_;
  wire _007_;
  wire _008_;
  wire _009_;
  wire _010_;
  wire _011_;
  wire _012_;
  wire _013_;
  wire _014_;
  wire _015_;
  wire _016_;
  wire _017_;
  wire _018_;
  wire _019_;
  wire _020_;
  wire _021_;
  wire _022_;
  wire _023_;
  wire _024_;
  wire _025_;
  wire _026_;
  wire _027_;
  wire _028_;
  wire _029_;
  wire _030_;
  wire _031_;
  wire _032_;
  wire _033_;
  wire _034_;
  wire _035_;
  wire _036_;
  wire _037_;
  wire _038_;
  wire _039_;
  wire _040_;
  wire _041_;
  wire _042_;
  wire _043_;
  wire _044_;
  wire _045_;
  wire _046_;
  wire _047_;
  wire _048_;
  wire _049_;
  wire _050_;
  wire _051_;
  wire _052_;
  wire _053_;
  wire _054_;
  wire _055_;
  wire _056_;
  wire _057_;
  wire _058_;
  wire _059_;
  wire _060_;
  wire _061_;
  wire _062_;
  (* src = "reg_desplazante.v:2" *)
  input CLK;
  (* src = "reg_desplazante.v:7" *)
  input [3:0] D;
  (* src = "reg_desplazante.v:4" *)
  input DIR;
  (* src = "reg_desplazante.v:3" *)
  input ENB;
  (* src = "reg_desplazante.v:6" *)
  input [1:0] MODO;
  (* src = "reg_desplazante.v:8" *)
  output [3:0] Q;
  (* src = "reg_desplazante.v:5" *)
  input S_IN;
  (* src = "reg_desplazante.v:9" *)
  output S_OUT;
  NAND _063_ (
    .A(MODO[1]),
    .B(MODO[0]),
    .Y(_002_)
  );
  NAND _064_ (
    .A(_002_),
    .B(ENB),
    .Y(_003_)
  );
  NOT _065_ (
    .A(_003_),
    .Y(_004_)
  );
  NOR _066_ (
    .A(_004_),
    .B(Q[0]),
    .Y(_005_)
  );
  NOT _067_ (
    .A(MODO[0]),
    .Y(_006_)
  );
  NOT _068_ (
    .A(MODO[1]),
    .Y(_007_)
  );
  NAND _069_ (
    .A(_007_),
    .B(_006_),
    .Y(_008_)
  );
  NAND _070_ (
    .A(DIR),
    .B(Q[1]),
    .Y(_009_)
  );
  NOT _071_ (
    .A(_009_),
    .Y(_010_)
  );
  NOT _072_ (
    .A(S_IN),
    .Y(_011_)
  );
  NOR _073_ (
    .A(_011_),
    .B(DIR),
    .Y(_012_)
  );
  NOR _074_ (
    .A(_012_),
    .B(_010_),
    .Y(_013_)
  );
  NOR _075_ (
    .A(_013_),
    .B(_008_),
    .Y(_014_)
  );
  NOR _076_ (
    .A(MODO[1]),
    .B(_006_),
    .Y(_015_)
  );
  NOT _077_ (
    .A(DIR),
    .Y(_016_)
  );
  NAND _078_ (
    .A(_016_),
    .B(Q[3]),
    .Y(_017_)
  );
  NAND _079_ (
    .A(_017_),
    .B(_009_),
    .Y(_018_)
  );
  NAND _080_ (
    .A(_018_),
    .B(_015_),
    .Y(_019_)
  );
  NOT _081_ (
    .A(D[0]),
    .Y(_020_)
  );
  NAND _082_ (
    .A(MODO[1]),
    .B(_006_),
    .Y(_021_)
  );
  NOR _083_ (
    .A(_021_),
    .B(_020_),
    .Y(_022_)
  );
  NOR _084_ (
    .A(_022_),
    .B(_003_),
    .Y(_023_)
  );
  NAND _085_ (
    .A(_023_),
    .B(_019_),
    .Y(_024_)
  );
  NOR _086_ (
    .A(_024_),
    .B(_014_),
    .Y(_025_)
  );
  NOR _087_ (
    .A(_025_),
    .B(_005_),
    .Y(_000_[0])
  );
  NAND _088_ (
    .A(_003_),
    .B(Q[1]),
    .Y(_026_)
  );
  NOR _089_ (
    .A(_007_),
    .B(MODO[0]),
    .Y(_027_)
  );
  NAND _090_ (
    .A(_027_),
    .B(D[1]),
    .Y(_028_)
  );
  NOT _091_ (
    .A(Q[2]),
    .Y(_029_)
  );
  NAND _092_ (
    .A(_029_),
    .B(DIR),
    .Y(_030_)
  );
  NOR _093_ (
    .A(Q[0]),
    .B(DIR),
    .Y(_031_)
  );
  NOR _094_ (
    .A(_031_),
    .B(MODO[1]),
    .Y(_032_)
  );
  NAND _095_ (
    .A(_032_),
    .B(_030_),
    .Y(_033_)
  );
  NAND _096_ (
    .A(_033_),
    .B(_028_),
    .Y(_034_)
  );
  NAND _097_ (
    .A(_034_),
    .B(ENB),
    .Y(_035_)
  );
  NAND _098_ (
    .A(_035_),
    .B(_026_),
    .Y(_000_[1])
  );
  NAND _099_ (
    .A(_003_),
    .B(Q[2]),
    .Y(_036_)
  );
  NAND _100_ (
    .A(_027_),
    .B(D[2]),
    .Y(_037_)
  );
  NOR _101_ (
    .A(_016_),
    .B(Q[3]),
    .Y(_038_)
  );
  NOR _102_ (
    .A(DIR),
    .B(Q[1]),
    .Y(_039_)
  );
  NOR _103_ (
    .A(_039_),
    .B(_038_),
    .Y(_040_)
  );
  NAND _104_ (
    .A(_040_),
    .B(_007_),
    .Y(_041_)
  );
  NAND _105_ (
    .A(_041_),
    .B(_037_),
    .Y(_042_)
  );
  NAND _106_ (
    .A(_042_),
    .B(ENB),
    .Y(_043_)
  );
  NAND _107_ (
    .A(_043_),
    .B(_036_),
    .Y(_000_[2])
  );
  NOR _108_ (
    .A(_004_),
    .B(Q[3]),
    .Y(_044_)
  );
  NOR _109_ (
    .A(_029_),
    .B(DIR),
    .Y(_045_)
  );
  NOR _110_ (
    .A(_011_),
    .B(_016_),
    .Y(_046_)
  );
  NOR _111_ (
    .A(_046_),
    .B(_045_),
    .Y(_047_)
  );
  NOR _112_ (
    .A(_047_),
    .B(_008_),
    .Y(_048_)
  );
  NAND _113_ (
    .A(Q[2]),
    .B(_016_),
    .Y(_049_)
  );
  NAND _114_ (
    .A(Q[0]),
    .B(DIR),
    .Y(_050_)
  );
  NAND _115_ (
    .A(_050_),
    .B(_049_),
    .Y(_051_)
  );
  NAND _116_ (
    .A(_051_),
    .B(_015_),
    .Y(_052_)
  );
  NOT _117_ (
    .A(D[3]),
    .Y(_053_)
  );
  NOR _118_ (
    .A(_021_),
    .B(_053_),
    .Y(_054_)
  );
  NOR _119_ (
    .A(_054_),
    .B(_003_),
    .Y(_055_)
  );
  NAND _120_ (
    .A(_055_),
    .B(_052_),
    .Y(_056_)
  );
  NOR _121_ (
    .A(_056_),
    .B(_048_),
    .Y(_057_)
  );
  NOR _122_ (
    .A(_057_),
    .B(_044_),
    .Y(_000_[3])
  );
  NAND _123_ (
    .A(_003_),
    .B(S_OUT),
    .Y(_058_)
  );
  NAND _124_ (
    .A(_050_),
    .B(_017_),
    .Y(_059_)
  );
  NOT _125_ (
    .A(ENB),
    .Y(_060_)
  );
  NOR _126_ (
    .A(_008_),
    .B(_060_),
    .Y(_061_)
  );
  NAND _127_ (
    .A(_061_),
    .B(_059_),
    .Y(_062_)
  );
  NAND _128_ (
    .A(_062_),
    .B(_058_),
    .Y(_001_)
  );
  DFF _129_ (
    .C(CLK),
    .D(_000_[0]),
    .Q(Q[0])
  );
  DFF _130_ (
    .C(CLK),
    .D(_000_[1]),
    .Q(Q[1])
  );
  DFF _131_ (
    .C(CLK),
    .D(_000_[2]),
    .Q(Q[2])
  );
  DFF _132_ (
    .C(CLK),
    .D(_000_[3]),
    .Q(Q[3])
  );
  DFF _133_ (
    .C(CLK),
    .D(_001_),
    .Q(S_OUT)
  );
endmodule

Digitales2/Tarea5/probador.v
module probador
  ( 
    output reg 	     CLK,
    output reg 	     ENB,
    output reg 	     DIR,
    output reg 	     S_IN,
    output reg [1:0] MODO,
    output reg [3:0] D
    );


   initial
     begin

        CLK <= 0;
        ENB <= 0;
        S_IN <= 1;
	D <= 4'b0000;
        MODO <= 2'b10;
        DIR <= 0;

	#42 ENB <= 1;

        #10 $display("   Parallel charge");
        #30 D <= 4'b0001;
        #30 D <= 4'b0011;
        #30 D <= 4'b0111;
        #30 D <= 4'b1111;
	
        //Rotation to the left
        #100 $display("    Rotation to the left");
        D <= 4'b0000;
        MODO <= 2'b10;

        #100 MODO <= 2'b00;

        //Rotation to the right
        #200 $display("   Rotation to the right");
        DIR <= 1;
        S_IN <= 0;

        //Circular rotation to the left
        #200 $display("   Circular rotation to the left");
        MODO <= 2'b10;
        D <= 4'b0111;

        #200 MODO <= 2'b01;
        DIR <= 0;

        //Circular rotation to the right
        #200 $display("   Circular rotation to the right");
        DIR <= 1;

     end

   
   always
     begin
        #20 CLK <= ~CLK;
     end


endmodule // probador

Digitales2/Tarea5/reg_desplazante_tb.v
`timescale 1ns/100ps
`include "synth.v"
`include "probador.v"


module reg_desplazante_tb ();

   //uut inputs
   wire CLK;
   wire ENB;
   wire DIR;
   wire S_IN;
   wire [1:0] MODO;
   wire [3:0] D;

   //uut outputs
   wire [3:0] Q;
   wire       S_OUT;


   probador prob (
		  .CLK(CLK),
		  .ENB(ENB),
		  .DIR(DIR),
		  .S_IN(S_IN),
		  .MODO(MODO),
		  .D(D)
		  );

   //Instantiate the unit under test
   reg_desplazante uut (
			.CLK(CLK),
			.ENB(ENB),
			.DIR(DIR),
			.S_IN(S_IN),
			.MODO(MODO),
			.D(D),
			.Q(Q),
			.S_OUT(S_OUT)
			);

   initial
     begin
	$dumpfile("reg_desplazante.vcd");
	$dumpvars();
	#1500 $finish;
     end


   always @ (posedge CLK)
     begin
	$monitor("At time %t, Q = %4b, S_OUT = %b ", $time, Q, S_OUT);
     end

endmodule // reg_desplazante_tb

Digitales2/Tarea5/Tarea5AndresAlvaradoB30316/vlib/standar_lib.v
module BUF(A, Y);
   input A;
   output Y;
   assign Y = A;
endmodule

module NOT(A, Y);
   input A;
   output Y;
   assign Y = ~A;
endmodule

module NAND(A, B, Y);
   input A, B;
   output Y;
   assign Y = ~(A & B);
endmodule

module NOR(A, B, Y);
   input A, B;
   output Y;
   assign Y = ~(A | B);
endmodule

module DFF(C, D, Q);
   input C, D;
   output reg Q;
   always @(posedge C)
     Q <= D;
endmodule

module DFFSR(C, D, Q, S, R);
   input C, D, S, R;
   output reg Q;
   always @(posedge C, posedge S, posedge R)
     if (S)
       Q <= 1'b1;
     else if (R)
       Q <= 1'b0;
     else
       Q <= D;
endmodule

Digitales2/Tarea5/reg_desplazante.vcd
$date
	Sun May 20 15:57:50 2018
$end
$version
	Icarus Verilog
$end
$timescale
	100ps
$end
$scope module BUF $end
$var wire 1 ! A $end
$var wire 1 " Y $end
$upscope $end
$scope module DFFSR $end
$var wire 1 # C $end
$var wire 1 $ D $end
$var wire 1 % R $end
$var wire 1 & S $end
$var reg 1 ' Q $end
$upscope $end
$scope module reg_desplazante_tb $end
$var wire 1 ( S_OUT $end
$var wire 1 ) S_IN $end
$var wire 4 * Q [3:0] $end
$var wire 2 + MODO [1:0] $end
$var wire 1 , ENB $end
$var wire 1 - DIR $end
$var wire 4 . D [3:0] $end
$var wire 1 / CLK $end
$scope module prob $end
$var reg 1 / CLK $end
$var reg 4 0 D [3:0] $end
$var reg 1 - DIR $end
$var reg 1 , ENB $end
$var reg 2 1 MODO [1:0] $end
$var reg 1 ) S_IN $end
$upscope $end
$scope module uut $end
$var wire 1 / CLK $end
$var wire 4 2 D [3:0] $end
$var wire 1 - DIR $end
$var wire 1 , ENB $end
$var wire 2 3 MODO [1:0] $end
$var wire 1 ) S_IN $end
$var wire 1 4 _062_ $end
$var wire 1 5 _061_ $end
$var wire 1 6 _060_ $end
$var wire 1 7 _059_ $end
$var wire 1 8 _058_ $end
$var wire 1 9 _057_ $end
$var wire 1 : _056_ $end
$var wire 1 ; _055_ $end
$var wire 1 < _054_ $end
$var wire 1 = _053_ $end
$var wire 1 > _052_ $end
$var wire 1 ? _051_ $end
$var wire 1 @ _050_ $end
$var wire 1 A _049_ $end
$var wire 1 B _048_ $end
$var wire 1 C _047_ $end
$var wire 1 D _046_ $end
$var wire 1 E _045_ $end
$var wire 1 F _044_ $end
$var wire 1 G _043_ $end
$var wire 1 H _042_ $end
$var wire 1 I _041_ $end
$var wire 1 J _040_ $end
$var wire 1 K _039_ $end
$var wire 1 L _038_ $end
$var wire 1 M _037_ $end
$var wire 1 N _036_ $end
$var wire 1 O _035_ $end
$var wire 1 P _034_ $end
$var wire 1 Q _033_ $end
$var wire 1 R _032_ $end
$var wire 1 S _031_ $end
$var wire 1 T _030_ $end
$var wire 1 U _029_ $end
$var wire 1 V _028_ $end
$var wire 1 W _027_ $end
$var wire 1 X _026_ $end
$var wire 1 Y _025_ $end
$var wire 1 Z _024_ $end
$var wire 1 [ _023_ $end
$var wire 1 \ _022_ $end
$var wire 1 ] _021_ $end
$var wire 1 ^ _020_ $end
$var wire 1 _ _019_ $end
$var wire 1 ` _018_ $end
$var wire 1 a _017_ $end
$var wire 1 b _016_ $end
$var wire 1 c _015_ $end
$var wire 1 d _014_ $end
$var wire 1 e _013_ $end
$var wire 1 f _012_ $end
$var wire 1 g _011_ $end
$var wire 1 h _010_ $end
$var wire 1 i _009_ $end
$var wire 1 j _008_ $end
$var wire 1 k _007_ $end
$var wire 1 l _006_ $end
$var wire 1 m _005_ $end
$var wire 1 n _004_ $end
$var wire 1 o _003_ $end
$var wire 1 p _002_ $end
$var wire 1 q _001_ $end
$var wire 4 r _000_ [3:0] $end
$var wire 1 ( S_OUT $end
$var wire 4 s Q [3:0] $end
$scope module _063_ $end
$var wire 1 t A $end
$var wire 1 u B $end
$var wire 1 p Y $end
$upscope $end
$scope module _064_ $end
$var wire 1 p A $end
$var wire 1 , B $end
$var wire 1 o Y $end
$upscope $end
$scope module _065_ $end
$var wire 1 o A $end
$var wire 1 n Y $end
$upscope $end
$scope module _066_ $end
$var wire 1 n A $end
$var wire 1 v B $end
$var wire 1 m Y $end
$upscope $end
$scope module _067_ $end
$var wire 1 w A $end
$var wire 1 l Y $end
$upscope $end
$scope module _068_ $end
$var wire 1 x A $end
$var wire 1 k Y $end
$upscope $end
$scope module _069_ $end
$var wire 1 k A $end
$var wire 1 l B $end
$var wire 1 j Y $end
$upscope $end
$scope module _070_ $end
$var wire 1 - A $end
$var wire 1 y B $end
$var wire 1 i Y $end
$upscope $end
$scope module _071_ $end
$var wire 1 i A $end
$var wire 1 h Y $end
$upscope $end
$scope module _072_ $end
$var wire 1 ) A $end
$var wire 1 g Y $end
$upscope $end
$scope module _073_ $end
$var wire 1 g A $end
$var wire 1 - B $end
$var wire 1 f Y $end
$upscope $end
$scope module _074_ $end
$var wire 1 f A $end
$var wire 1 h B $end
$var wire 1 e Y $end
$upscope $end
$scope module _075_ $end
$var wire 1 e A $end
$var wire 1 j B $end
$var wire 1 d Y $end
$upscope $end
$scope module _076_ $end
$var wire 1 z A $end
$var wire 1 l B $end
$var wire 1 c Y $end
$upscope $end
$scope module _077_ $end
$var wire 1 - A $end
$var wire 1 b Y $end
$upscope $end
$scope module _078_ $end
$var wire 1 b A $end
$var wire 1 { B $end
$var wire 1 a Y $end
$upscope $end
$scope module _079_ $end
$var wire 1 a A $end
$var wire 1 i B $end
$var wire 1 ` Y $end
$upscope $end
$scope module _080_ $end
$var wire 1 ` A $end
$var wire 1 c B $end
$var wire 1 _ Y $end
$upscope $end
$scope module _081_ $end
$var wire 1 | A $end
$var wire 1 ^ Y $end
$upscope $end
$scope module _082_ $end
$var wire 1 } A $end
$var wire 1 l B $end
$var wire 1 ] Y $end
$upscope $end
$scope module _083_ $end
$var wire 1 ] A $end
$var wire 1 ^ B $end
$var wire 1 \ Y $end
$upscope $end
$scope module _084_ $end
$var wire 1 \ A $end
$var wire 1 o B $end
$var wire 1 [ Y $end
$upscope $end
$scope module _085_ $end
$var wire 1 [ A $end
$var wire 1 _ B $end
$var wire 1 Z Y $end
$upscope $end
$scope module _086_ $end
$var wire 1 Z A $end
$var wire 1 d B $end
$var wire 1 Y Y $end
$upscope $end
$scope module _087_ $end
$var wire 1 Y A $end
$var wire 1 m B $end
$var wire 1 ~ Y $end
$upscope $end
$scope module _088_ $end
$var wire 1 o A $end
$var wire 1 !" B $end
$var wire 1 X Y $end
$upscope $end
$scope module _089_ $end
$var wire 1 k A $end
$var wire 1 "" B $end
$var wire 1 W Y $end
$upscope $end
$scope module _090_ $end
$var wire 1 W A $end
$var wire 1 #" B $end
$var wire 1 V Y $end
$upscope $end
$scope module _091_ $end
$var wire 1 $" A $end
$var wire 1 U Y $end
$upscope $end
$scope module _092_ $end
$var wire 1 U A $end
$var wire 1 - B $end
$var wire 1 T Y $end
$upscope $end
$scope module _093_ $end
$var wire 1 %" A $end
$var wire 1 - B $end
$var wire 1 S Y $end
$upscope $end
$scope module _094_ $end
$var wire 1 S A $end
$var wire 1 &" B $end
$var wire 1 R Y $end
$upscope $end
$scope module _095_ $end
$var wire 1 R A $end
$var wire 1 T B $end
$var wire 1 Q Y $end
$upscope $end
$scope module _096_ $end
$var wire 1 Q A $end
$var wire 1 V B $end
$var wire 1 P Y $end
$upscope $end
$scope module _097_ $end
$var wire 1 P A $end
$var wire 1 , B $end
$var wire 1 O Y $end
$upscope $end
$scope module _098_ $end
$var wire 1 O A $end
$var wire 1 X B $end
$var wire 1 '" Y $end
$upscope $end
$scope module _099_ $end
$var wire 1 o A $end
$var wire 1 (" B $end
$var wire 1 N Y $end
$upscope $end
$scope module _100_ $end
$var wire 1 W A $end
$var wire 1 )" B $end
$var wire 1 M Y $end
$upscope $end
$scope module _101_ $end
$var wire 1 b A $end
$var wire 1 *" B $end
$var wire 1 L Y $end
$upscope $end
$scope module _102_ $end
$var wire 1 - A $end
$var wire 1 +" B $end
$var wire 1 K Y $end
$upscope $end
$scope module _103_ $end
$var wire 1 K A $end
$var wire 1 L B $end
$var wire 1 J Y $end
$upscope $end
$scope module _104_ $end
$var wire 1 J A $end
$var wire 1 k B $end
$var wire 1 I Y $end
$upscope $end
$scope module _105_ $end
$var wire 1 I A $end
$var wire 1 M B $end
$var wire 1 H Y $end
$upscope $end
$scope module _106_ $end
$var wire 1 H A $end
$var wire 1 , B $end
$var wire 1 G Y $end
$upscope $end
$scope module _107_ $end
$var wire 1 G A $end
$var wire 1 N B $end
$var wire 1 ," Y $end
$upscope $end
$scope module _108_ $end
$var wire 1 n A $end
$var wire 1 -" B $end
$var wire 1 F Y $end
$upscope $end
$scope module _109_ $end
$var wire 1 U A $end
$var wire 1 - B $end
$var wire 1 E Y $end
$upscope $end
$scope module _110_ $end
$var wire 1 g A $end
$var wire 1 b B $end
$var wire 1 D Y $end
$upscope $end
$scope module _111_ $end
$var wire 1 D A $end
$var wire 1 E B $end
$var wire 1 C Y $end
$upscope $end
$scope module _112_ $end
$var wire 1 C A $end
$var wire 1 j B $end
$var wire 1 B Y $end
$upscope $end
$scope module _113_ $end
$var wire 1 ." A $end
$var wire 1 b B $end
$var wire 1 A Y $end
$upscope $end
$scope module _114_ $end
$var wire 1 /" A $end
$var wire 1 - B $end
$var wire 1 @ Y $end
$upscope $end
$scope module _115_ $end
$var wire 1 @ A $end
$var wire 1 A B $end
$var wire 1 ? Y $end
$upscope $end
$scope module _116_ $end
$var wire 1 ? A $end
$var wire 1 c B $end
$var wire 1 > Y $end
$upscope $end
$scope module _117_ $end
$var wire 1 0" A $end
$var wire 1 = Y $end
$upscope $end
$scope module _118_ $end
$var wire 1 ] A $end
$var wire 1 = B $end
$var wire 1 < Y $end
$upscope $end
$scope module _119_ $end
$var wire 1 < A $end
$var wire 1 o B $end
$var wire 1 ; Y $end
$upscope $end
$scope module _120_ $end
$var wire 1 ; A $end
$var wire 1 > B $end
$var wire 1 : Y $end
$upscope $end
$scope module _121_ $end
$var wire 1 : A $end
$var wire 1 B B $end
$var wire 1 9 Y $end
$upscope $end
$scope module _122_ $end
$var wire 1 9 A $end
$var wire 1 F B $end
$var wire 1 1" Y $end
$upscope $end
$scope module _123_ $end
$var wire 1 o A $end
$var wire 1 8 Y $end
$var wire 1 ( B $end
$upscope $end
$scope module _124_ $end
$var wire 1 @ A $end
$var wire 1 a B $end
$var wire 1 7 Y $end
$upscope $end
$scope module _125_ $end
$var wire 1 , A $end
$var wire 1 6 Y $end
$upscope $end
$scope module _126_ $end
$var wire 1 j A $end
$var wire 1 6 B $end
$var wire 1 5 Y $end
$upscope $end
$scope module _127_ $end
$var wire 1 5 A $end
$var wire 1 7 B $end
$var wire 1 4 Y $end
$upscope $end
$scope module _128_ $end
$var wire 1 4 A $end
$var wire 1 8 B $end
$var wire 1 q Y $end
$upscope $end
$scope module _129_ $end
$var wire 1 / C $end
$var wire 1 2" D $end
$var reg 1 3" Q $end
$upscope $end
$scope module _130_ $end
$var wire 1 / C $end
$var wire 1 4" D $end
$var reg 1 5" Q $end
$upscope $end
$scope module _131_ $end
$var wire 1 / C $end
$var wire 1 6" D $end
$var reg 1 7" Q $end
$upscope $end
$scope module _132_ $end
$var wire 1 / C $end
$var wire 1 8" D $end
$var reg 1 9" Q $end
$upscope $end
$scope module _133_ $end
$var wire 1 / C $end
$var wire 1 q D $end
$var reg 1 ( Q $end
$upscope $end
$upscope $end
$upscope $end
$enddefinitions $end
#0
$dumpvars
x9"
x8"
x7"
x6"
x5"
x4"
x3"
x2"
x1"
00"
x/"
x."
x-"
x,"
x+"
x*"
0)"
x("
x'"
1&"
x%"
x$"
0#"
0""
x!"
x~
1}
0|
x{
1z
xy
1x
0w
xv
0u
1t
bx s
bx r
xq
1p
1o
0n
xm
1l
0k
1j
1i
0h
0g
1f
0e
0d
0c
1b
xa
x`
1_
1^
0]
0\
0[
1Z
0Y
xX
1W
1V
xU
1T
xS
0R
1Q
0P
1O
xN
1M
0L
xK
xJ
1I
0H
1G
xF
xE
0D
xC
0B
xA
1@
x?
1>
1=
0<
0;
1:
09
x8
x7
16
05
14
b10 3
b0 2
b10 1
b0 0
0/
b0 .
0-
0,
b10 +
bx *
1)
x(
x'
z&
z%
z$
z#
z"
z!
$end
#200
1/
#400
0/
#420
02"
08"
1Y
19
0~
01"
04"
06"
0Z
0'"
b0 r
0,"
0:
0q
0m
0F
1[
1X
1N
1;
18
1n
0o
06
1,
#600
1C
0`
07
0?
0J
0E
1a
1A
1K
1S
1U
0-"
0*"
0{
0."
0("
0$"
0+"
0!"
0y
0/"
0%"
0v
0(
09"
07"
05"
b0 *
b0 s
03"
1/
#800
0/
#820
12"
b1 r
1~
0Y
1Z
0[
1\
0^
1|
b1 .
b1 0
b1 2
#1000
0S
1/"
1%"
1v
b1 *
b1 s
13"
1/
#1120
14"
b11 r
1'"
0O
1P
0V
1#"
b11 .
b11 0
b11 2
#1200
0/
#1400
1J
0K
1+"
1!"
1y
b11 *
b11 s
15"
1/
#1420
16"
b111 r
1,"
0G
1H
0M
1)"
b111 .
b111 0
b111 2
#1600
0/
#1720
18"
b1111 r
11"
09
1:
0;
1<
0=
10"
b1111 .
b1111 0
b1111 2
#1800
0C
1?
1`
17
1E
0A
0a
0U
1."
1("
1$"
1-"
1*"
1{
17"
b1111 *
b1111 s
19"
1/
#2000
0/
#2200
1/
#2400
0/
#2600
1/
#2720
02"
08"
0~
01"
1Y
04"
06"
19
0'"
b0 r
0,"
0Z
0:
1O
1G
1[
1;
0P
0H
0\
0<
1V
1M
1^
1=
0|
0#"
0)"
00"
b0 .
b0 0
b0 2
#2800
0/
#3000
1C
0`
07
0?
0J
0E
1a
1A
1K
1S
1U
0-"
0*"
0{
0."
0("
0$"
0+"
0!"
0y
0/"
0%"
0v
09"
07"
05"
b0 *
b0 s
03"
1/
#3200
0/
#3400
1/
#3600
0/
#3720
12"
b1 r
1~
0Y
1d
15
0j
0W
1]
1k
0t
0x
0z
0}
0&"
b0 +
b0 1
b0 3
#3800
14"
b11 r
1'"
0O
1P
0Q
1R
0S
1/"
1%"
1v
b1 *
b1 s
13"
1/
#4000
0/
#4200
16"
b111 r
1,"
0G
1H
0I
1J
0K
1+"
1!"
1y
b11 *
b11 s
15"
1/
#4400
0/
#4600
18"
b1111 r
11"
09
1B
0C
1?
1E
0A
0U
1."
1("
1$"
b111 *
b111 s
17"
1/
#4800
0/
#5000
1q
04
1`
17
0a
1-"
1*"
1{
b1111 *
b1111 s
19"
1/
#5200
0/
#5400
1(
1/
#5600
0/
#5720
12"
08"
1~
b111 r
01"
0Y
19
1d
0B
0e
1C
1h
1a
1A
0i
0f
0E
0@
1g
0b
0)
1-
#5800
06"
b11 r
0,"
1G
0H
1I
0J
1L
0-"
0*"
0{
b111 *
b111 s
09"
1/
#6000
0/
#6200
04"
b1 r
0'"
1O
0P
1Q
0T
1U
0."
0("
0$"
b11 *
b11 s
07"
1/
#6400
0/
#6600
02"
b0 r
0~
1Y
0d
1e
0`
0h
1i
0+"
0!"
0y
b1 *
b1 s
05"
1/
#6800
0/
#7000
0q
14
0?
07
1@
0/"
0%"
0v
b0 *
b0 s
03"
1/
#7200
0/
#7400
0(
1/
#7600
0/
#7720
12"
14"
16"
1~
1'"
b111 r
1,"
0Y
0O
0G
1Z
1P
1H
0[
05
0V
0M
1\
1j
1W
0]
0R
0^
0k
1|
1#"
1)"
1t
1x
1z
1}
1&"
b111 .
b111 0
b111 2
b10 +
b10 1
b10 3
#7800
0e
1`
1?
17
1T
1h
0i
0@
0U
1."
1("
1$"
1+"
1!"
1y
1/"
1%"
1v
17"
15"
b111 *
b111 s
13"
1/
#8000
0/
#8200
1/
#8400
0/
#8600
1/
#8800
0/
#9000
1/
#9200
0/
#9400
1/
#9600
0/
#9720
18"
02"
11"
0~
16"
09
1Y
b1110 r
1,"
1:
0Z
0G
0I
0>
1[
1H
1e
1J
0\
1V
1M
0Q
0`
0C
1?
07
1c
0h
0L
0A
1]
0W
1R
1i
1E
1@
0l
1k
1b
0t
1u
1w
0x
0z
0}
1""
0&"
0-
b1 +
b1 1
b1 3
#9800
04"
12"
0'"
b1101 r
1~
1O
0Y
0P
1Z
1Q
0_
0R
1`
17
1S
0a
0/"
0%"
0v
1-"
1*"
1{
03"
b1110 *
b1110 s
19"
1/
#10000
0/
#10200
06"
14"
0,"
b1011 r
1'"
1G
0O
0H
1P
1I
0Q
0J
1R
1K
0S
0+"
0!"
0y
1/"
1%"
1v
05"
b1101 *
b1101 s
13"
1/
#10400
0/
#10600
16"
08"
1,"
b111 r
01"
0G
19
1H
0:
0I
1>
1C
1J
0?
0E
0K
1A
1U
1+"
1!"
1y
0."
0("
0$"
15"
b1011 *
b1011 s
07"
1/
#10800
0/
#11000
02"
18"
0~
b1110 r
11"
1Y
09
0Z
1:
1_
0>
0C
0`
07
1?
1E
1a
0A
0U
0-"
0*"
0{
1."
1("
1$"
09"
b111 *
b111 s
17"
1/
#11200
0/
#11400
04"
12"
0'"
b1101 r
1~
1O
0Y
0P
1Z
1Q
0_
0R
1`
17
1S
0a
0/"
0%"
0v
1-"
1*"
1{
03"
b1110 *
b1110 s
19"
1/
#11600
0/
#11720
08"
01"
14"
b111 r
1'"
19
0O
0:
1P
1>
0Q
0e
07
0?
1R
1C
1h
1a
1A
0i
0S
0E
0b
1-
#11800
06"
18"
0,"
b1011 r
11"
1G
09
0H
1:
1I
0>
0J
1?
17
1L
0@
0-"
0*"
0{
1/"
1%"
1v
09"
b111 *
b111 s
13"
1/
#12000
0/
#12200
16"
04"
1,"
b1101 r
0'"
0G
1O
1H
0P
0I
1Q
1J
0T
0L
1U
0."
0("
0$"
1-"
1*"
1{
07"
b1011 *
b1011 s
19"
1/
#12400
0/
#12600
02"
14"
0~
b1110 r
1'"
1Y
0O
0Z
1P
1_
0Q
1e
0`
1T
0h
1i
0U
1."
1("
1$"
0+"
0!"
0y
17"
b1101 *
b1101 s
05"
1/
#12800
0/
#13000
08"
12"
01"
b111 r
1~
19
0Y
0:
1Z
1>
0_
0e
0?
07
1`
1h
1@
0i
0/"
0%"
0v
1+"
1!"
1y
03"
b1110 *
b1110 s
15"
1/
#13200
0/
#13400
06"
18"
0,"
b1011 r
11"
1G
09
0H
1:
1I
0>
0J
1?
17
1L
0@
0-"
0*"
0{
1/"
1%"
1v
09"
b111 *
b111 s
13"
1/
#13600
0/
#13800
16"
04"
1,"
b1101 r
0'"
0G
1O
1H
0P
0I
1Q
1J
0T
0L
1U
0."
0("
0$"
1-"
1*"
1{
07"
b1011 *
b1011 s
19"
1/
#14000
0/
#14200
02"
14"
0~
b1110 r
1'"
1Y
0O
0Z
1P
1_
0Q
1e
0`
1T
0h
1i
0U
1."
1("
1$"
0+"
0!"
0y
17"
b1101 *
b1101 s
05"
1/
#14400
0/
#14600
08"
12"
01"
b111 r
1~
19
0Y
0:
1Z
1>
0_
0e
0?
07
1`
1h
1@
0i
0/"
0%"
0v
1+"
1!"
1y
03"
b1110 *
b1110 s
15"
1/
#14800
0/
#15000
06"
18"
0,"
b1011 r
11"
1G
09
0H
1:
1I
0>
0J
1?
17
1L
0@
0-"
0*"
0{
1/"
1%"
1v
09"
b111 *
b111 s
13"
1/
